Workbook

Sheet ScenMap_OLD
I1: C
I2: ar6_r10 | J2: timeslice
A5: * | B5: Oname | C5: Name | D5: Desc | E5: Ldesc | H5: Scen | I5: ="sg_"&I2 -> sg_ar6_r10 | J5: ="sg_"&J2 -> sg_timeslice
A6: 1 | B6: ="vstacks_"&VLOOKUP(A6,$S$6:$T$18,2,FALSE)&"~"&TEXT(O6,"0000") -> vstacks_s1p1v1_d~0001 | C6: =H6 -> e 1.5 deg no OS.e3d | H6: =_xlfn.TEXTJOIN(".",TRUE,I6:J6) -> e 1.5 deg no OS.e3d | I6: e 1.5 deg no OS | J6: =Q6 -> e3d | L6: Limit warming to 1.5°C (>50%) with no or limited overshoot | O6: 1 | Q6: =VLOOKUP(A6,$S$6:$U$17,3,FALSE) -> e3d | S6: 1 | T6: s1p1v1_d | U6: e3d
A7: 1 | B7: ="vstacks_"&VLOOKUP(A7,$S$6:$T$18,2,FALSE)&"~"&TEXT(O7,"0000") -> vstacks_s1p1v1_d~0002 | C7: =H7 -> d 1.5 deg OS.e3d | H7: =_xlfn.TEXTJOIN(".",TRUE,I7:J7) -> d 1.5 deg OS.e3d | I7: d 1.5 deg OS | J7: =Q7 -> e3d | L7: Limit warming to 1.5°C (>67%) with high overshoot | O7: 2 | Q7: =VLOOKUP(A7,$S$6:$U$17,3,FALSE) -> e3d | S7: 2 | T7: s3p3v3_d | U7: d9d
A8: 1 | B8: ="vstacks_"&VLOOKUP(A8,$S$6:$T$18,2,FALSE)&"~"&TEXT(O8,"0000") -> vstacks_s1p1v1_d~0003 | C8: =H8 -> c 2 deg (67%).e3d | H8: =_xlfn.TEXTJOIN(".",TRUE,I8:J8) -> c 2 deg (67%).e3d | I8: c 2 deg (67%) | J8: =Q8 -> e3d | L8: Limit warming to 2°C (>67%) with higher action post-2030 | O8: 3 | Q8: =VLOOKUP(A8,$S$6:$U$17,3,FALSE) -> e3d | S8: 3 | T8: s2_w | U8: b2w
A9: 1 | B9: ="vstacks_"&VLOOKUP(A9,$S$6:$T$18,2,FALSE)&"~"&TEXT(O9,"0000") -> vstacks_s1p1v1_d~0004 | C9: =H9 -> b 2 deg (50%).e3d | H9: =_xlfn.TEXTJOIN(".",TRUE,I9:J9) -> b 2 deg (50%).e3d | I9: b 2 deg (50%) | J9: =Q9 -> e3d | L9: Limit warming to 2°C (>50%) with immediate action | O9: 4 | Q9: =VLOOKUP(A9,$S$6:$U$17,3,FALSE) -> e3d | S9: 4 | T9: s2_w_p2_d | U9: a2w2d
A10: 1 | B10: ="vstacks_"&VLOOKUP(A10,$S$6:$T$18,2,FALSE)&"~"&TEXT(O10,"0000") -> vstacks_s1p1v1_d~0005 | C10: =H10 -> a 3 deg.e3d | H10: =_xlfn.TEXTJOIN(".",TRUE,I10:J10) -> a 3 deg.e3d | I10: a 3 deg | J10: =Q10 -> e3d | L10: Likely above 3°C warming with limited mitigation | O10: 5 | Q10: =VLOOKUP(A10,$S$6:$U$17,3,FALSE) -> e3d | S10: 5 | T10: ts12_clu | U10: hTS12c
A11: =A6+1 -> 2 | B11: ="vstacks_"&VLOOKUP(A11,$S$6:$T$18,2,FALSE)&"~"&TEXT(O11,"0000") -> vstacks_s3p3v3_d~0001 | C11: =H11 -> e 1.5 deg no OS.d9d | H11: =_xlfn.TEXTJOIN(".",TRUE,I11:J11) -> e 1.5 deg no OS.d9d | I11: =I6 -> e 1.5 deg no OS | J11: =Q11 -> d9d | O11: =O6 -> 1 | Q11: =VLOOKUP(A11,$S$6:$U$17,3,FALSE) -> d9d | S11: 6 | T11: ts24_clu | U11: gTS24c
A12: =A7+1 -> 2 | B12: ="vstacks_"&VLOOKUP(A12,$S$6:$T$18,2,FALSE)&"~"&TEXT(O12,"0000") -> vstacks_s3p3v3_d~0002 | C12: =H12 -> d 1.5 deg OS.d9d | H12: =_xlfn.TEXTJOIN(".",TRUE,I12:J12) -> d 1.5 deg OS.d9d | I12: =I7 -> d 1.5 deg OS | J12: =Q12 -> d9d | O12: =O7 -> 2 | Q12: =VLOOKUP(A12,$S$6:$U$17,3,FALSE) -> d9d | S12: 7 | T12: ts48_clu | U12: fTS48c
A13: =A8+1 -> 2 | B13: ="vstacks_"&VLOOKUP(A13,$S$6:$T$18,2,FALSE)&"~"&TEXT(O13,"0000") -> vstacks_s3p3v3_d~0003 | C13: =H13 -> c 2 deg (67%).d9d | H13: =_xlfn.TEXTJOIN(".",TRUE,I13:J13) -> c 2 deg (67%).d9d | I13: =I8 -> c 2 deg (67%) | J13: =Q13 -> d9d | O13: =O8 -> 3 | Q13: =VLOOKUP(A13,$S$6:$U$17,3,FALSE) -> d9d | S13: 8 | T13: s5p5v5_d | U13: c15d
A14: =A9+1 -> 2 | B14: ="vstacks_"&VLOOKUP(A14,$S$6:$T$18,2,FALSE)&"~"&TEXT(O14,"0000") -> vstacks_s3p3v3_d~0004 | C14: =H14 -> b 2 deg (50%).d9d | H14: =_xlfn.TEXTJOIN(".",TRUE,I14:J14) -> b 2 deg (50%).d9d | I14: =I9 -> b 2 deg (50%) | J14: =Q14 -> d9d | O14: =O9 -> 4 | Q14: =VLOOKUP(A14,$S$6:$U$17,3,FALSE) -> d9d | S14: 9 | T14: ts_12 | U14: iTS12
A15: =A10+1 -> 2 | B15: ="vstacks_"&VLOOKUP(A15,$S$6:$T$18,2,FALSE)&"~"&TEXT(O15,"0000") -> vstacks_s3p3v3_d~0005 | C15: =H15 -> a 3 deg.d9d | H15: =_xlfn.TEXTJOIN(".",TRUE,I15:J15) -> a 3 deg.d9d | I15: =I10 -> a 3 deg | J15: =Q15 -> d9d | O15: =O10 -> 5 | Q15: =VLOOKUP(A15,$S$6:$U$17,3,FALSE) -> d9d | S15: 10 | T15: ts_annual | U15: jAnn
A16: =A11+1 -> 3 | B16: ="vstacks_"&VLOOKUP(A16,$S$6:$T$18,2,FALSE)&"~"&TEXT(O16,"0000") -> vstacks_s2_w~0001 | C16: =H16 -> e 1.5 deg no OS.b2w | H16: =_xlfn.TEXTJOIN(".",TRUE,I16:J16) -> e 1.5 deg no OS.b2w | I16: =I11 -> e 1.5 deg no OS | J16: =Q16 -> b2w | O16: =O11 -> 1 | Q16: =VLOOKUP(A16,$S$6:$U$17,3,FALSE) -> b2w | S16: 11 | T16: s1_d | U16: f3d
A17: =A12+1 -> 3 | B17: ="vstacks_"&VLOOKUP(A17,$S$6:$T$18,2,FALSE)&"~"&TEXT(O17,"0000") -> vstacks_s2_w~0002 | C17: =H17 -> d 1.5 deg OS.b2w | H17: =_xlfn.TEXTJOIN(".",TRUE,I17:J17) -> d 1.5 deg OS.b2w | I17: =I12 -> d 1.5 deg OS | J17: =Q17 -> b2w | O17: =O12 -> 2 | Q17: =VLOOKUP(A17,$S$6:$U$17,3,FALSE) -> b2w
A18: =A13+1 -> 3 | B18: ="vstacks_"&VLOOKUP(A18,$S$6:$T$18,2,FALSE)&"~"&TEXT(O18,"0000") -> vstacks_s2_w~0003 | C18: =H18 -> c 2 deg (67%).b2w | H18: =_xlfn.TEXTJOIN(".",TRUE,I18:J18) -> c 2 deg (67%).b2w | I18: =I13 -> c 2 deg (67%) | J18: =Q18 -> b2w | O18: =O13 -> 3 | Q18: =VLOOKUP(A18,$S$6:$U$17,3,FALSE) -> b2w
A19: =A14+1 -> 3 | B19: ="vstacks_"&VLOOKUP(A19,$S$6:$T$18,2,FALSE)&"~"&TEXT(O19,"0000") -> vstacks_s2_w~0004 | C19: =H19 -> b 2 deg (50%).b2w | H19: =_xlfn.TEXTJOIN(".",TRUE,I19:J19) -> b 2 deg (50%).b2w | I19: =I14 -> b 2 deg (50%) | J19: =Q19 -> b2w | O19: =O14 -> 4 | Q19: =VLOOKUP(A19,$S$6:$U$17,3,FALSE) -> b2w
A20: =A15+1 -> 3 | B20: ="vstacks_"&VLOOKUP(A20,$S$6:$T$18,2,FALSE)&"~"&TEXT(O20,"0000") -> vstacks_s2_w~0005 | C20: =H20 -> a 3 deg.b2w | H20: =_xlfn.TEXTJOIN(".",TRUE,I20:J20) -> a 3 deg.b2w | I20: =I15 -> a 3 deg | J20: =Q20 -> b2w | O20: =O15 -> 5 | Q20: =VLOOKUP(A20,$S$6:$U$17,3,FALSE) -> b2w
A21: =A16+1 -> 4 | B21: ="vstacks_"&VLOOKUP(A21,$S$6:$T$18,2,FALSE)&"~"&TEXT(O21,"0000") -> vstacks_s2_w_p2_d~0001 | C21: =H21 -> e 1.5 deg no OS.a2w2d | H21: =_xlfn.TEXTJOIN(".",TRUE,I21:J21) -> e 1.5 deg no OS.a2w2d | I21: =I16 -> e 1.5 deg no OS | J21: =Q21 -> a2w2d | O21: =O16 -> 1 | Q21: =VLOOKUP(A21,$S$6:$U$17,3,FALSE) -> a2w2d
A22: =A17+1 -> 4 | B22: ="vstacks_"&VLOOKUP(A22,$S$6:$T$18,2,FALSE)&"~"&TEXT(O22,"0000") -> vstacks_s2_w_p2_d~0002 | C22: =H22 -> d 1.5 deg OS.a2w2d | H22: =_xlfn.TEXTJOIN(".",TRUE,I22:J22) -> d 1.5 deg OS.a2w2d | I22: =I17 -> d 1.5 deg OS | J22: =Q22 -> a2w2d | O22: =O17 -> 2 | Q22: =VLOOKUP(A22,$S$6:$U$17,3,FALSE) -> a2w2d
A23: =A18+1 -> 4 | B23: ="vstacks_"&VLOOKUP(A23,$S$6:$T$18,2,FALSE)&"~"&TEXT(O23,"0000") -> vstacks_s2_w_p2_d~0003 | C23: =H23 -> c 2 deg (67%).a2w2d | H23: =_xlfn.TEXTJOIN(".",TRUE,I23:J23) -> c 2 deg (67%).a2w2d | I23: =I18 -> c 2 deg (67%) | J23: =Q23 -> a2w2d | O23: =O18 -> 3 | Q23: =VLOOKUP(A23,$S$6:$U$17,3,FALSE) -> a2w2d
A24: =A19+1 -> 4 | B24: ="vstacks_"&VLOOKUP(A24,$S$6:$T$18,2,FALSE)&"~"&TEXT(O24,"0000") -> vstacks_s2_w_p2_d~0004 | C24: =H24 -> b 2 deg (50%).a2w2d | H24: =_xlfn.TEXTJOIN(".",TRUE,I24:J24) -> b 2 deg (50%).a2w2d | I24: =I19 -> b 2 deg (50%) | J24: =Q24 -> a2w2d | O24: =O19 -> 4 | Q24: =VLOOKUP(A24,$S$6:$U$17,3,FALSE) -> a2w2d
A25: =A20+1 -> 4 | B25: ="vstacks_"&VLOOKUP(A25,$S$6:$T$18,2,FALSE)&"~"&TEXT(O25,"0000") -> vstacks_s2_w_p2_d~0005 | C25: =H25 -> a 3 deg.a2w2d | H25: =_xlfn.TEXTJOIN(".",TRUE,I25:J25) -> a 3 deg.a2w2d | I25: =I20 -> a 3 deg | J25: =Q25 -> a2w2d | O25: =O20 -> 5 | Q25: =VLOOKUP(A25,$S$6:$U$17,3,FALSE) -> a2w2d
A26: =A21+1 -> 5 | B26: ="vstacks_"&VLOOKUP(A26,$S$6:$T$18,2,FALSE)&"~"&TEXT(O26,"0000") -> vstacks_ts12_clu~0001 | C26: =H26 -> e 1.5 deg no OS.hTS12c | H26: =_xlfn.TEXTJOIN(".",TRUE,I26:J26) -> e 1.5 deg no OS.hTS12c | I26: =I21 -> e 1.5 deg no OS | J26: =Q26 -> hTS12c | O26: =O21 -> 1 | Q26: =VLOOKUP(A26,$S$6:$U$17,3,FALSE) -> hTS12c
A27: =A22+1 -> 5 | B27: ="vstacks_"&VLOOKUP(A27,$S$6:$T$18,2,FALSE)&"~"&TEXT(O27,"0000") -> vstacks_ts12_clu~0002 | C27: =H27 -> d 1.5 deg OS.hTS12c | H27: =_xlfn.TEXTJOIN(".",TRUE,I27:J27) -> d 1.5 deg OS.hTS12c | I27: =I22 -> d 1.5 deg OS | J27: =Q27 -> hTS12c | O27: =O22 -> 2 | Q27: =VLOOKUP(A27,$S$6:$U$17,3,FALSE) -> hTS12c
A28: =A23+1 -> 5 | B28: ="vstacks_"&VLOOKUP(A28,$S$6:$T$18,2,FALSE)&"~"&TEXT(O28,"0000") -> vstacks_ts12_clu~0003 | C28: =H28 -> c 2 deg (67%).hTS12c | H28: =_xlfn.TEXTJOIN(".",TRUE,I28:J28) -> c 2 deg (67%).hTS12c | I28: =I23 -> c 2 deg (67%) | J28: =Q28 -> hTS12c | O28: =O23 -> 3 | Q28: =VLOOKUP(A28,$S$6:$U$17,3,FALSE) -> hTS12c
... A60: =A55+1 -> 11 | B60: ="vstacks_"&VLOOKUP(A60,$S$6:$T$18,2,FALSE)&"~"&TEXT(O60,"0000") -> vstacks_s1_d~0005 | C60: =H60 -> a 3 deg.f3d | H60: =_xlfn.TEXTJOIN(".",TRUE,I60:J60) -> a 3 deg.f3d | I60: =I55 -> a 3 deg | J60: =Q60 -> f3d | O60: =O55 -> 5 | Q60: =VLOOKUP(A60,$S$6:$U$17,3,FALSE) -> f3d

Sheet ScenMap
I1: C
I2: ar6_r10 | J2: timeslice
B4: ~ScenMap | H4: ~ScenG
B5: Oname | C5: Name | D5: Desc | E5: Ldesc | H5: Scen | I5: ="sg_"&I2 -> sg_ar6_r10 | J5: ="sg_"&J2 -> sg_timeslice
B6: ="vs~"&TEXT(O6,"0000") -> vs~0001 | C6: =H6 -> e 1.5 deg no OS.e3d | H6: =_xlfn.TEXTJOIN(".",TRUE,I6:J6) -> e 1.5 deg no OS.e3d | I6: =VLOOKUP(Q6,$W$6:$X$12,2,FALSE) -> e 1.5 deg no OS | J6: =VLOOKUP(P6,$T$6:$U$16,2,FALSE) -> e3d | L6: Limit warming to 1.5°C (>50%) with no or limited overshoot | O6: 1 | P6: s1p1v1_d | Q6: C1 | S6: 1 | T6: s1p1v1_d | U6: e3d | W6: C1 | X6: e 1.5 deg no OS
B7: ="vs~"&TEXT(O7,"0000") -> vs~0002 | C7: =H7 -> e 1.5 deg no OS.d9d | H7: =_xlfn.TEXTJOIN(".",TRUE,I7:J7) -> e 1.5 deg no OS.d9d | I7: =VLOOKUP(Q7,$W$6:$X$12,2,FALSE) -> e 1.5 deg no OS | J7: =VLOOKUP(P7,$T$6:$U$16,2,FALSE) -> d9d | L7: Limit warming to 1.5°C (>67%) with high overshoot | O7: 2 | P7: s3p3v3_d | Q7: C1 | S7: 2 | T7: s3p3v3_d | U7: d9d | W7: C2 | X7: d 1.5 deg OS
B8: ="vs~"&TEXT(O8,"0000") -> vs~0003 | C8: =H8 -> e 1.5 deg no OS.b2w | H8: =_xlfn.TEXTJOIN(".",TRUE,I8:J8) -> e 1.5 deg no OS.b2w | I8: =VLOOKUP(Q8,$W$6:$X$12,2,FALSE) -> e 1.5 deg no OS | J8: =VLOOKUP(P8,$T$6:$U$16,2,FALSE) -> b2w | L8: Limit warming to 2°C (>67%) with higher action post-2030 | O8: 3 | P8: s2_w | Q8: C1 | S8: 3 | T8: s2_w | U8: b2w | W8: C3 | X8: c 2 deg (67%)
B9: ="vs~"&TEXT(O9,"0000") -> vs~0004 | C9: =H9 -> e 1.5 deg no OS.a2w2d | H9: =_xlfn.TEXTJOIN(".",TRUE,I9:J9) -> e 1.5 deg no OS.a2w2d | I9: =VLOOKUP(Q9,$W$6:$X$12,2,FALSE) -> e 1.5 deg no OS | J9: =VLOOKUP(P9,$T$6:$U$16,2,FALSE) -> a2w2d | L9: Limit warming to 2°C (>50%) with immediate action | O9: 4 | P9: s2_w_p2_d | Q9: C1 | S9: 4 | T9: s2_w_p2_d | U9: a2w2d | W9: C4 | X9: b 2 deg (50%)
B10: ="vs~"&TEXT(O10,"0000") -> vs~0005 | C10: =H10 -> e 1.5 deg no OS.hTS12c | H10: =_xlfn.TEXTJOIN(".",TRUE,I10:J10) -> e 1.5 deg no OS.hTS12c | I10: =VLOOKUP(Q10,$W$6:$X$12,2,FALSE) -> e 1.5 deg no OS | J10: =VLOOKUP(P10,$T$6:$U$16,2,FALSE) -> hTS12c | L10: Likely above 3°C warming with limited mitigation | O10: 5 | P10: ts12_clu | Q10: C1 | S10: 5 | T10: ts12_clu | U10: hTS12c | W10: C7 | X10: a 3 deg
B11: ="vs~"&TEXT(O11,"0000") -> vs~0006 | C11: =H11 -> e 1.5 deg no OS.gTS24c | H11: =_xlfn.TEXTJOIN(".",TRUE,I11:J11) -> e 1.5 deg no OS.gTS24c | I11: =VLOOKUP(Q11,$W$6:$X$12,2,FALSE) -> e 1.5 deg no OS | J11: =VLOOKUP(P11,$T$6:$U$16,2,FALSE) -> gTS24c | O11: 6 | P11: ts24_clu | Q11: C1 | S11: 6 | T11: ts24_clu | U11: gTS24c
B12: ="vs~"&TEXT(O12,"0000") -> vs~0007 | C12: =H12 -> e 1.5 deg no OS.fTS48c | H12: =_xlfn.TEXTJOIN(".",TRUE,I12:J12) -> e 1.5 deg no OS.fTS48c | I12: =VLOOKUP(Q12,$W$6:$X$12,2,FALSE) -> e 1.5 deg no OS | J12: =VLOOKUP(P12,$T$6:$U$16,2,FALSE) -> fTS48c | O12: 7 | P12: ts48_clu | Q12: C1 | S12: 7 | T12: ts48_clu | U12: fTS48c
B13: ="vs~"&TEXT(O13,"0000") -> vs~0008 | C13: =H13 -> e 1.5 deg no OS.c15d | H13: =_xlfn.TEXTJOIN(".",TRUE,I13:J13) -> e 1.5 deg no OS.c15d | I13: =VLOOKUP(Q13,$W$6:$X$12,2,FALSE) -> e 1.5 deg no OS | J13: =VLOOKUP(P13,$T$6:$U$16,2,FALSE) -> c15d | O13: 8 | P13: s5p5v5_d | Q13: C1 | S13: 8 | T13: s5p5v5_d | U13: c15d
B14: ="vs~"&TEXT(O14,"0000") -> vs~0009 | C14: =H14 -> e 1.5 deg no OS.f1d | H14: =_xlfn.TEXTJOIN(".",TRUE,I14:J14) -> e 1.5 deg no OS.f1d | I14: =VLOOKUP(Q14,$W$6:$X$12,2,FALSE) -> e 1.5 deg no OS | J14: =VLOOKUP(P14,$T$6:$U$16,2,FALSE) -> f1d | O14: 9 | P14: s1_d | Q14: C1 | S14: 9 | T14: ts_12 | U14: iTS12
B15: ="vs~"&TEXT(O15,"0000") -> vs~0010 | C15: =H15 -> e 1.5 deg no OS.jAnn | H15: =_xlfn.TEXTJOIN(".",TRUE,I15:J15) -> e 1.5 deg no OS.jAnn | I15: =VLOOKUP(Q15,$W$6:$X$12,2,FALSE) -> e 1.5 deg no OS | J15: =VLOOKUP(P15,$T$6:$U$16,2,FALSE) -> jAnn | O15: 10 | P15: ts_annual | Q15: C1 | S15: 10 | T15: ts_annual | U15: jAnn
B16: ="vs~"&TEXT(O16,"0000") -> vs~0011 | C16: =H16 -> e 1.5 deg no OS.iTS12 | H16: =_xlfn.TEXTJOIN(".",TRUE,I16:J16) -> e 1.5 deg no OS.iTS12 | I16: =VLOOKUP(Q16,$W$6:$X$12,2,FALSE) -> e 1.5 deg no OS | J16: =VLOOKUP(P16,$T$6:$U$16,2,FALSE) -> iTS12 | O16: 11 | P16: ts_12 | Q16: C1 | S16: 11 | T16: s1_d | U16: f1d
B17: ="vs~"&TEXT(O17,"0000") -> vs~0012 | C17: =H17 -> d 1.5 deg OS.e3d | H17: =_xlfn.TEXTJOIN(".",TRUE,I17:J17) -> d 1.5 deg OS.e3d | I17: =VLOOKUP(Q17,$W$6:$X$12,2,FALSE) -> d 1.5 deg OS | J17: =VLOOKUP(P17,$T$6:$U$16,2,FALSE) -> e3d | O17: 12 | P17: s1p1v1_d | Q17: C2
B18: ="vs~"&TEXT(O18,"0000") -> vs~0013 | C18: =H18 -> d 1.5 deg OS.d9d | H18: =_xlfn.TEXTJOIN(".",TRUE,I18:J18) -> d 1.5 deg OS.d9d | I18: =VLOOKUP(Q18,$W$6:$X$12,2,FALSE) -> d 1.5 deg OS | J18: =VLOOKUP(P18,$T$6:$U$16,2,FALSE) -> d9d | O18: 13 | P18: s3p3v3_d | Q18: C2
B19: ="vs~"&TEXT(O19,"0000") -> vs~0014 | C19: =H19 -> d 1.5 deg OS.b2w | H19: =_xlfn.TEXTJOIN(".",TRUE,I19:J19) -> d 1.5 deg OS.b2w | I19: =VLOOKUP(Q19,$W$6:$X$12,2,FALSE) -> d 1.5 deg OS | J19: =VLOOKUP(P19,$T$6:$U$16,2,FALSE) -> b2w | O19: 14 | P19: s2_w | Q19: C2
B20: ="vs~"&TEXT(O20,"0000") -> vs~0015 | C20: =H20 -> d 1.5 deg OS.a2w2d | H20: =_xlfn.TEXTJOIN(".",TRUE,I20:J20) -> d 1.5 deg OS.a2w2d | I20: =VLOOKUP(Q20,$W$6:$X$12,2,FALSE) -> d 1.5 deg OS | J20: =VLOOKUP(P20,$T$6:$U$16,2,FALSE) -> a2w2d | O20: 15 | P20: s2_w_p2_d | Q20: C2
B21: ="vs~"&TEXT(O21,"0000") -> vs~0016 | C21: =H21 -> d 1.5 deg OS.hTS12c | H21: =_xlfn.TEXTJOIN(".",TRUE,I21:J21) -> d 1.5 deg OS.hTS12c | I21: =VLOOKUP(Q21,$W$6:$X$12,2,FALSE) -> d 1.5 deg OS | J21: =VLOOKUP(P21,$T$6:$U$16,2,FALSE) -> hTS12c | O21: 16 | P21: ts12_clu | Q21: C2
B22: ="vs~"&TEXT(O22,"0000") -> vs~0017 | C22: =H22 -> d 1.5 deg OS.gTS24c | H22: =_xlfn.TEXTJOIN(".",TRUE,I22:J22) -> d 1.5 deg OS.gTS24c | I22: =VLOOKUP(Q22,$W$6:$X$12,2,FALSE) -> d 1.5 deg OS | J22: =VLOOKUP(P22,$T$6:$U$16,2,FALSE) -> gTS24c | O22: 17 | P22: ts24_clu | Q22: C2
B23: ="vs~"&TEXT(O23,"0000") -> vs~0018 | C23: =H23 -> d 1.5 deg OS.fTS48c | H23: =_xlfn.TEXTJOIN(".",TRUE,I23:J23) -> d 1.5 deg OS.fTS48c | I23: =VLOOKUP(Q23,$W$6:$X$12,2,FALSE) -> d 1.5 deg OS | J23: =VLOOKUP(P23,$T$6:$U$16,2,FALSE) -> fTS48c | O23: 18 | P23: ts48_clu | Q23: C2
B24: ="vs~"&TEXT(O24,"0000") -> vs~0019 | C24: =H24 -> d 1.5 deg OS.c15d | H24: =_xlfn.TEXTJOIN(".",TRUE,I24:J24) -> d 1.5 deg OS.c15d | I24: =VLOOKUP(Q24,$W$6:$X$12,2,FALSE) -> d 1.5 deg OS | J24: =VLOOKUP(P24,$T$6:$U$16,2,FALSE) -> c15d | O24: 19 | P24: s5p5v5_d | Q24: C2
B25: ="vs~"&TEXT(O25,"0000") -> vs~0020 | C25: =H25 -> d 1.5 deg OS.f1d | H25: =_xlfn.TEXTJOIN(".",TRUE,I25:J25) -> d 1.5 deg OS.f1d | I25: =VLOOKUP(Q25,$W$6:$X$12,2,FALSE) -> d 1.5 deg OS | J25: =VLOOKUP(P25,$T$6:$U$16,2,FALSE) -> f1d | O25: 20 | P25: s1_d | Q25: C2
B26: ="vs~"&TEXT(O26,"0000") -> vs~0021 | C26: =H26 -> d 1.5 deg OS.jAnn | H26: =_xlfn.TEXTJOIN(".",TRUE,I26:J26) -> d 1.5 deg OS.jAnn | I26: =VLOOKUP(Q26,$W$6:$X$12,2,FALSE) -> d 1.5 deg OS | J26: =VLOOKUP(P26,$T$6:$U$16,2,FALSE) -> jAnn | O26: 21 | P26: ts_annual | Q26: C2
B27: ="vs~"&TEXT(O27,"0000") -> vs~0022 | C27: =H27 -> d 1.5 deg OS.iTS12 | H27: =_xlfn.TEXTJOIN(".",TRUE,I27:J27) -> d 1.5 deg OS.iTS12 | I27: =VLOOKUP(Q27,$W$6:$X$12,2,FALSE) -> d 1.5 deg OS | J27: =VLOOKUP(P27,$T$6:$U$16,2,FALSE) -> iTS12 | O27: 22 | P27: ts_12 | Q27: C2
B28: ="vs~"&TEXT(O28,"0000") -> vs~0023 | C28: =H28 -> c 2 deg (67%).e3d | H28: =_xlfn.TEXTJOIN(".",TRUE,I28:J28) -> c 2 deg (67%).e3d | I28: =VLOOKUP(Q28,$W$6:$X$12,2,FALSE) -> c 2 deg (67%) | J28: =VLOOKUP(P28,$T$6:$U$16,2,FALSE) -> e3d | O28: 23 | P28: s1p1v1_d | Q28: C3
... B60: ="vs~"&TEXT(O60,"0000") -> vs~0055 | C60: =H60 -> a 3 deg.iTS12 | H60: =_xlfn.TEXTJOIN(".",TRUE,I60:J60) -> a 3 deg.iTS12 | I60: =VLOOKUP(Q60,$W$6:$X$12,2,FALSE) -> a 3 deg | J60: =VLOOKUP(P60,$T$6:$U$16,2,FALSE) -> iTS12 | O60: 55 | P60: ts_12 | Q60: C7

Sheet TS_Defs
A1: ~TS_Defs
A2: Attribute | B2: WAttribute | C2: PSET_Set | D2: PSET_PN | E2: PSET_PD | F2: PSET_CI | G2: PSET_CO | H2: CSET_Set | I2: CSET_CN | J2: CSET_CD | K2: Unit | L2: TS | M2: UC_N | N2: Name | O2: Desc | P2: Ldesc | Q2: show_me | R2: discard
A3: VAR_CAP | C3: ELE,STG,IRE | D3: -ElcAgg*,-*EV*,-g[_]* | K3: GW | N3: Elec Capacity
A4: VAR_NCAP | C4: ELE,STG,IRE | D4: -ElcAgg*,-*EV*,-g[_]* | K4: GW | N4: Elec New Capacity | T4: group_by
A5: VAR_FOUT | C5: ELE,IRE | D5: -ElcAgg*,-*EV*,-g[_]* | I5: ELC,ELC_???-???*,e[_]* | K5: Twh | N5: Elec Production | T5: p | U5: process
A6: VAR_POUT | C6: ELE,STG,IRE,-Grid | H6: NRG | I6: -elc_roadtransport | K6: Twh2GW | N6: Power | Q6: t
A7: VAR_FOUT | I7: CO2 | K7: kt | N7: CO2_emission
A8: VAR_FOUT | I8: CO2Captured | K8: ktneg | N8: CO2_captured
A9: Cost_INV | C9: ELE,STG,IRE | D9: -ElcAgg*,-*EV* | K9: m$2020 | N9: Cost_Investment
A10: EQ_COMBALM | B10: VAR_COMPRD | H10: NRG | K10: $/Mwh | N10: Price_NRG | P10: Prices of all NRG - native TS | Q10: ct
A11: EQ_COMBALM | B11: VAR_COMPRD | I11: co2net | K11: 000$/t | N11: Price_CO2
A12: User_conFXM | K12: m$/UCU | N12: UC_shadowprice | P12: shadow prices of all Ucs | Q12: u
A13: VAR_NCAPR | B13: VAR_NCAP | K13: $/Mwh | N13: LCOE | Q13: p
A14: Reg_wobj | K14: m$2020 | N14: SysCost_NPV | Q14: u
A15: Reg_ACost | K15: m$2020 | N15: SysCost_Annual | Q15: u

Sheet TS_ratios
C1: ~TS_Ratios
C2: var_num | D2: var_den | E2: Name | F2: Unit | G2: show_me | H2: ignore | I2: include_null | J2: include_dim | K2: Ldesc
C3: Elec Production | D3: Elec Capacity | E3: Capacity_factor | F3: Twh/GW | G3: p | I3: y | J3: p

Sheet geolocation
B9: ~geolocation
B10: region | C10: lat | D10: lng
B11: p_CH1 | C11: 47.544891 | D11: 7.9712762
B12: p_CH11 | C12: 47.304725 | D12: 7.7779032
B13: p_CH12 | C13: 47.19085 | D13: 8.9859184
B14: p_CH13 | C14: 47.178826 | D14: 8.9144144
B15: p_CH14 | C15: 47.09248 | D15: 7.6486786
B16: p_CH15 | C16: 47.075251 | D16: 8.2262358
B17: p_CH16 | C17: 46.998666 | D17: 9.1028854
B18: p_CH17 | C18: 46.948265 | D18: 9.4806532
B19: p_CH18 | C19: 46.881454 | D19: 8.9862022
B20: p_CH19 | C20: 46.810115 | D20: 8.0932617
B21: p_CH2 | C21: 47.539987 | D21: 7.9955896
B22: p_CH20 | C22: 46.788976 | D22: 8.1290423
... B191: rez_CHE_25 | C191: 47.03733 | D191: 10.161302

Sheet process_map_geo
B2: ~process_map
B3: dimension | C3: description | D3: pset_set
B4: grid_node | C4: p_CH1 | D4: p_CH1
B5: grid_node | C5: p_CH11 | D5: p_CH11
B6: grid_node | C6: p_CH12 | D6: p_CH12
B7: grid_node | C7: p_CH13 | D7: p_CH13
B8: grid_node | C8: p_CH14 | D8: p_CH14
B9: grid_node | C9: p_CH15 | D9: p_CH15
B10: grid_node | C10: p_CH16 | D10: p_CH16
B11: grid_node | C11: p_CH17 | D11: p_CH17
B12: grid_node | C12: p_CH18 | D12: p_CH18
B13: grid_node | C13: p_CH19 | D13: p_CH19
B14: grid_node | C14: p_CH2 | D14: p_CH2
... B184: grid_node | C184: rez_CHE_25 | D184: rez_CHE_25

Sheet Sankey
A3: DeACT TS_Defs: Snk_attr=SANKEY Grid Flows
A4: Attribute | B4: PSET_Set | C4: PSET_PN | D4: PSET_PD | E4: PSET_CI | F4: PSET_CO | G4: CSET_Set | H4: CSET_CN | I4: CSET_CD | J4: Unit | K4: TS | L4: UC_N | M4: Name | N4: Desc | O4: Ldesc | P4: show_me | Q4: ignore | R4: T_neg_andor | S4: downscale_option
A5: VAR_FOUT | B5: =_xlfn.TEXTJOIN(",",TRUE,PSet_MAP!$A$3:$A$49) -> CCGT,Int Comb,Gas_Oil Steam,OCGT (Peaker),Subcritical Coal,Supercritical Coal,IGCC,Bio Power,Solar Util,Wind onshore,Wind offshore,Geothermal P,Hydro Dam,Hydro RoR,Nuclear P,Nuclear SMR,Hydro pumped stg,Util Batt Stg,EV Batt,Demand,Transformers Dn,Transformers Up,Grid-220V,Grid-400V,Grid-380V,Grid-225V,Grid-330V,Grid-275V,Grid-420V,Grid-300V,Grid-500V,Grid-750V,Grid-450V,Grid-515V,Grid-525V,Grid-320V,Grid-150V,Grid-270V,Grid-350V,Grid-250V,Grid-200V,Grid-236V,Grid-600V,Aggregators,DUMMY_IMP | G5: =_xlfn.TEXTJOIN(",",TRUE,CSET_MAP!$A$3:$A$43) -> Elec-220V,Elec-400V,Elec-380V,Elec-225V,Elec-330V,Elec-275V,Elec-420V,Elec-300V,Elec-500V,Elec-750V,Elec-450V,Elec-515V,Elec-525V,Elec-320V,Elec-150V,Elec-270V,Elec-350V,Elec-250V,Elec-200V,Elec-236V,Elec-600V,Solar elec,Wind elec,hydrogen,ELC,buildings,industry,transport,EVs,fossil,renewable,bioenergy,nuclear | J5: TWh | M5: <cset>_Src_<pset> | S5: -1
A6: VAR_FIN | B6: =_xlfn.TEXTJOIN(",",TRUE,PSet_MAP!$A$3:$A$49) -> CCGT,Int Comb,Gas_Oil Steam,OCGT (Peaker),Subcritical Coal,Supercritical Coal,IGCC,Bio Power,Solar Util,Wind onshore,Wind offshore,Geothermal P,Hydro Dam,Hydro RoR,Nuclear P,Nuclear SMR,Hydro pumped stg,Util Batt Stg,EV Batt,Demand,Transformers Dn,Transformers Up,Grid-220V,Grid-400V,Grid-380V,Grid-225V,Grid-330V,Grid-275V,Grid-420V,Grid-300V,Grid-500V,Grid-750V,Grid-450V,Grid-515V,Grid-525V,Grid-320V,Grid-150V,Grid-270V,Grid-350V,Grid-250V,Grid-200V,Grid-236V,Grid-600V,Aggregators,DUMMY_IMP | G6: =_xlfn.TEXTJOIN(",",TRUE,CSET_MAP!$A$3:$A$43) -> Elec-220V,Elec-400V,Elec-380V,Elec-225V,Elec-330V,Elec-275V,Elec-420V,Elec-300V,Elec-500V,Elec-750V,Elec-450V,Elec-515V,Elec-525V,Elec-320V,Elec-150V,Elec-270V,Elec-350V,Elec-250V,Elec-200V,Elec-236V,Elec-600V,Solar elec,Wind elec,hydrogen,ELC,buildings,industry,transport,EVs,fossil,renewable,bioenergy,nuclear | J6: TWh | M6: <cset>_Snk_<pset> | S6: -1
A10: ~TS_Defs: Snk_attr=SANKEY whole system
A11: Attribute | B11: PSET_Set | C11: PSET_PN | D11: PSET_PD | E11: PSET_CI | F11: PSET_CO | G11: CSET_Set | H11: CSET_CN | I11: CSET_CD | J11: Unit | K11: TS | L11: UC_N | M11: Name | N11: Desc | O11: Ldesc | P11: show_me | Q11: ignore | R11: T_neg_andor | S11: downscale_option
A12: * | B12: Fuels
A13: VAR_FOUT | F13: =H13 -> bioenergy,coal,gas,geothermal,hydro,hydrogen,nuclear,oil,solar,windon,windoff | H13: =_xlfn.TEXTJOIN(",",TRUE,CName_MAP!$A$3:$A$16) -> bioenergy,coal,gas,geothermal,hydro,hydrogen,nuclear,oil,solar,windon,windoff | J13: TWh | M13: <gen_cname>_src_<gen_pname> | S13: -1
A14: VAR_FIN | B14: =B5 -> CCGT,Int Comb,Gas_Oil Steam,OCGT (Peaker),Subcritical Coal,Supercritical Coal,IGCC,Bio Power,Solar Util,Wind onshore,Wind offshore,Geothermal P,Hydro Dam,Hydro RoR,Nuclear P,Nuclear SMR,Hydro pumped stg,Util Batt Stg,EV Batt,Demand,Transformers Dn,Transformers Up,Grid-220V,Grid-400V,Grid-380V,Grid-225V,Grid-330V,Grid-275V,Grid-420V,Grid-300V,Grid-500V,Grid-750V,Grid-450V,Grid-515V,Grid-525V,Grid-320V,Grid-150V,Grid-270V,Grid-350V,Grid-250V,Grid-200V,Grid-236V,Grid-600V,Aggregators,DUMMY_IMP | H14: =_xlfn.TEXTJOIN(",",TRUE,CName_MAP!$A$3:$A$16) -> bioenergy,coal,gas,geothermal,hydro,hydrogen,nuclear,oil,solar,windon,windoff | J14: TWh | M14: <gen_cname>_snk_<pset> | S14: -1
A15: * | B15: Electricity
A16: VAR_FOUT | B16: =_xlfn.TEXTJOIN(",",TRUE,PSet_MAP!$A$3:$A$49) -> CCGT,Int Comb,Gas_Oil Steam,OCGT (Peaker),Subcritical Coal,Supercritical Coal,IGCC,Bio Power,Solar Util,Wind onshore,Wind offshore,Geothermal P,Hydro Dam,Hydro RoR,Nuclear P,Nuclear SMR,Hydro pumped stg,Util Batt Stg,EV Batt,Demand,Transformers Dn,Transformers Up,Grid-220V,Grid-400V,Grid-380V,Grid-225V,Grid-330V,Grid-275V,Grid-420V,Grid-300V,Grid-500V,Grid-750V,Grid-450V,Grid-515V,Grid-525V,Grid-320V,Grid-150V,Grid-270V,Grid-350V,Grid-250V,Grid-200V,Grid-236V,Grid-600V,Aggregators,DUMMY_IMP | G16: =_xlfn.TEXTJOIN(",",TRUE,CSET_MAP!$A$3:$A$31) -> Elec-220V,Elec-400V,Elec-380V,Elec-225V,Elec-330V,Elec-275V,Elec-420V,Elec-300V,Elec-500V,Elec-750V,Elec-450V,Elec-515V,Elec-525V,Elec-320V,Elec-150V,Elec-270V,Elec-350V,Elec-250V,Elec-200V,Elec-236V,Elec-600V,Solar elec,Wind elec,hydrogen,ELC,buildings,industry,transport,EVs | J16: TWh | M16: <cset>_src_<pset> | S16: -1
A17: VAR_FIN | B17: =_xlfn.TEXTJOIN(",",TRUE,PSet_MAP!$A$3:$A$49) -> CCGT,Int Comb,Gas_Oil Steam,OCGT (Peaker),Subcritical Coal,Supercritical Coal,IGCC,Bio Power,Solar Util,Wind onshore,Wind offshore,Geothermal P,Hydro Dam,Hydro RoR,Nuclear P,Nuclear SMR,Hydro pumped stg,Util Batt Stg,EV Batt,Demand,Transformers Dn,Transformers Up,Grid-220V,Grid-400V,Grid-380V,Grid-225V,Grid-330V,Grid-275V,Grid-420V,Grid-300V,Grid-500V,Grid-750V,Grid-450V,Grid-515V,Grid-525V,Grid-320V,Grid-150V,Grid-270V,Grid-350V,Grid-250V,Grid-200V,Grid-236V,Grid-600V,Aggregators,DUMMY_IMP | G17: =_xlfn.TEXTJOIN(",",TRUE,CSET_MAP!$A$3:$A$31) -> Elec-220V,Elec-400V,Elec-380V,Elec-225V,Elec-330V,Elec-275V,Elec-420V,Elec-300V,Elec-500V,Elec-750V,Elec-450V,Elec-515V,Elec-525V,Elec-320V,Elec-150V,Elec-270V,Elec-350V,Elec-250V,Elec-200V,Elec-236V,Elec-600V,Solar elec,Wind elec,hydrogen,ELC,buildings,industry,transport,EVs | J17: TWh | M17: <cset>_snk_<pset> | S17: -1
A18: * | B18: Hydrogen
A19: VAR_FOUT | F19: =H19 -> hydrogen | H19: hydrogen | J19: TWh | M19: <gen_cname>_src_<gen_pname> | S19: -1
A20: VAR_FIN | F20: hydrogen | G20: =_xlfn.TEXTJOIN(",",TRUE,CSET_MAP!$A$3:$A$43) -> Elec-220V,Elec-400V,Elec-380V,Elec-225V,Elec-330V,Elec-275V,Elec-420V,Elec-300V,Elec-500V,Elec-750V,Elec-450V,Elec-515V,Elec-525V,Elec-320V,Elec-150V,Elec-270V,Elec-350V,Elec-250V,Elec-200V,Elec-236V,Elec-600V,Solar elec,Wind elec,hydrogen,ELC,buildings,industry,transport,EVs,fossil,renewable,bioenergy,nuclear | J20: TWh | M20: <cset>_snk_<gen_pname> | S20: -1
A23: VAR_FIN | E23: hydrogen | H23: hydrogen | J23: TWh | M23: <gen_cname>_snk_<gen_pname> | S23: -1

Sheet PSet_MAP
A1: ~Pset_Map
A2: Pset | B2: Desc | C2: Ldesc
A3: CCGT | B3: =A3 -> CCGT
A4: Int Comb | B4: =A4 -> Int Comb
A5: Gas_Oil Steam | B5: =A5 -> Gas_Oil Steam
A6: OCGT (Peaker) | B6: =A6 -> OCGT (Peaker)
A7: Subcritical Coal | B7: =A7 -> Subcritical Coal
A8: Supercritical Coal | B8: =A8 -> Supercritical Coal
A9: IGCC | B9: =A9 -> IGCC
A10: Bio Power | B10: =A10 -> Bio Power
A11: Solar Util | B11: =A11 -> Solar Util
A12: Wind onshore | B12: Onshore Wind
A13: Wind offshore | B13: Offshore Wind
A14: Geothermal P | B14: =A14 -> Geothermal P
A15: Hydro Dam | B15: =A15 -> Hydro Dam
A16: Hydro RoR | B16: =A16 -> Hydro RoR
A17: Nuclear P | B17: =A17 -> Nuclear P
A18: Nuclear SMR | B18: =A18 -> Nuclear SMR
A19: Hydro pumped stg | B19: =A19 -> Hydro pumped stg
A20: Util Batt Stg | B20: =A20 -> Util Batt Stg
A21: EV Batt | B21: =A21 -> EV Batt
A22: Demand | B22: =A22 -> Demand
A23: Transformers Dn | B23: =A23 -> Transformers Dn
A24: Transformers Up | B24: =A24 -> Transformers Up
A25: Grid-220V | B25: =A25 -> Grid-220V
... A47: DUMMY_IMP | B47: =A47 -> DUMMY_IMP

Sheet CSET_MAP
A1: ~Cset_Map
A2: Cset | B2: Desc | C2: Ldesc
A3: Elec-220V | B3: =A3 -> Elec-220V
A4: Elec-400V | B4: =A4 -> Elec-400V
A5: Elec-380V | B5: =A5 -> Elec-380V
A6: Elec-225V | B6: =A6 -> Elec-225V
A7: Elec-330V | B7: =A7 -> Elec-330V
A8: Elec-275V | B8: =A8 -> Elec-275V
A9: Elec-420V | B9: =A9 -> Elec-420V
A10: Elec-300V | B10: =A10 -> Elec-300V
A11: Elec-500V | B11: =A11 -> Elec-500V
A12: Elec-750V | B12: =A12 -> Elec-750V
A13: Elec-450V | B13: =A13 -> Elec-450V
A14: Elec-515V | B14: =A14 -> Elec-515V
... A23: Elec-600V | B23: =A23 -> Elec-600V
A24: Solar elec | B24: Electricity
A25: Wind elec | B25: Electricity
A26: hydrogen | B26: =A26 -> hydrogen
A27: ELC | B27: Electricity
A28: buildings | B28: =A28 -> buildings
A29: industry | B29: =A29 -> industry
A30: transport | B30: =A30 -> transport
A31: EVs | B31: =A31 -> EVs
A32: fossil | B32: =A32 -> fossil
A33: renewable | B33: =A33 -> renewable
A34: bioenergy | B34: =A34 -> bioenergy
A35: nuclear | B35: =A35 -> nuclear

Sheet CName_MAP
A1: ~CName_Map
A2: CName | B2: Desc | C2: Ldesc
A3: bioenergy | B3: =A3 -> bioenergy
A4: coal | B4: =A4 -> coal
A5: gas | B5: =A5 -> gas
A6: geothermal | B6: =A6 -> geothermal
A7: hydro | B7: =A7 -> hydro
A8: hydrogen | B8: =A8 -> hydrogen
A9: nuclear | B9: =A9 -> nuclear
A10: oil | B10: =A10 -> oil
A11: solar | B11: =A11 -> solar
A12: windon | B12: wind onshore
A13: windoff | B13: wind offshore

Sheet timeslice map
A1: ~Timeslice_Map
A2: dimension | B2: name | C2: description
A3: ts_type | B3: *,-s?a* | C3: hourly
A4: ts_type | B4: s?a* | C4: aggregated
A5: ts_season | B5: S1* | C5: =LEFT(B5,2) -> S1
A6: ts_season | B6: S2* | C6: =LEFT(B6,2) -> S2
A7: ts_season | B7: S3* | C7: =LEFT(B7,2) -> S3
A8: ts_season | B8: S4* | C8: =LEFT(B8,2) -> S4
A9: ts_season | B9: S5* | C9: =LEFT(B9,2) -> S5
A10: ts_season | B10: S6* | C10: =LEFT(B10,2) -> S6

Sheet process map
A1: ~process_map
A2: dimension | B2: name | C2: description | D2: pset_set | E2: pset_ci | F2: pset_co | G2: pset_pd
A3: old_new | B3: * | C3: new
A4: old_new | B4: ep* | C4: old
A5: Tech | C5: =D5 -> CCGT | D5: CCGT
A6: Tech | C6: =D6 -> Int Comb | D6: Int Comb
A7: Tech | C7: =D7 -> Gas_Oil Steam | D7: Gas_Oil Steam
A8: Tech | C8: =D8 -> OCGT (Peaker) | D8: OCGT (Peaker)
A9: Tech | C9: =D9 -> Subcritical Coal | D9: Subcritical Coal
A10: Tech | C10: =D10 -> Supercritical Coal | D10: Supercritical Coal
A11: Tech | C11: =D11 -> IGCC | D11: IGCC
A12: Tech | C12: =D12 -> Bio Power | D12: Bio Power
A13: Tech | C13: =D13 -> Solar Util | D13: Solar Util
A14: Tech | C14: =D14 -> Wind onshore | D14: Wind onshore
A15: Tech | C15: =D15 -> Wind offshore | D15: Wind offshore
A16: Tech | C16: =D16 -> Geothermal P | D16: Geothermal P
... A49: Tech | C49: =D49 -> DUMMY_IMP | D49: DUMMY_IMP
A50: Tech | B50: *ccs | C50: Coal CCS | E50: coal
A51: Tech | B51: *ccs | C51: Gas CCS | E51: gas
A52: Tech | B52: *ccs-rf | C52: Coal CCS Retrofit | E52: coal
A53: Tech | B53: *ccs-rf | C53: Gas CCS Retrofit | E53: gas
A54: Tech | B54: ElcAgg_Solar | C54: Solar
A55: Tech | B55: ElcAgg_Wind | C55: Wind
A56: Tech | B56: Trd* | C56: Trade

Sheet commodity map
A1: ~commodity_map
A2: dimension | B2: name | C2: description | D2: cset_set | E2: cset_cd | F2: c_set_andor | G2: c_pos_andor | H2: c_neg_andor

Sheet ATS
A1: ~ATS
A2: Model | B2: Scen | C2: Region | D2: Varbl | E2: Unit | F2: Year | G2: Val

Sheet UnitConv
A1: ~UnitConv
A2: Model | B2: Unit1 | C2: Unit2 | D2: MultFact
A3: VS | B3: Twh2GW | C3: GW | D3: =1/8.76 -> 0.11415525
A4: VS | B4: Twh/GW | C4: % | D4: =1/8.76*100 -> 11.415525
A5: VS | B5: kt | C5: mt | D5: 0.001
A6: VS | B6: ktneg | C6: mt | D6: -0.001
A7: VS | B7: 000$/t | C7: $/tCO2 | D7: -1000
