Workbook

Sheet ScenMap_OLD
I1: C
I2: ar6_r10 | J2: timeslice
A5: * | B5: Oname | C5: Name | D5: Desc | E5: Ldesc | H5: Scen | I5: ="sg_"&I2 -> sg_ar6_r10 | J5: ="sg_"&J2 -> sg_timeslice
A6: 1 | B6: ="vstacks_"&VLOOKUP(A6,$S$6:$T$18,2,FALSE)&"~"&TEXT(O6,"0000") -> vstacks_s1p1v1_d~0001 | C6: =H6 -> e 1.5 deg no OS.e3d | H6: =_xlfn.TEXTJOIN(".",TRUE,I6:J6) -> e 1.5 deg no OS.e3d | I6: e 1.5 deg no OS | J6: =Q6 -> e3d | L6: Limit warming to 1.5°C (>50%) with no or limited overshoot | O6: 1 | Q6: =VLOOKUP(A6,$S$6:$U$17,3,FALSE) -> e3d | S6: 1 | T6: s1p1v1_d | U6: e3d
A7: 1 | B7: ="vstacks_"&VLOOKUP(A7,$S$6:$T$18,2,FALSE)&"~"&TEXT(O7,"0000") -> vstacks_s1p1v1_d~0002 | C7: =H7 -> d 1.5 deg OS.e3d | H7: =_xlfn.TEXTJOIN(".",TRUE,I7:J7) -> d 1.5 deg OS.e3d | I7: d 1.5 deg OS | J7: =Q7 -> e3d | L7: Limit warming to 1.5°C (>67%) with high overshoot | O7: 2 | Q7: =VLOOKUP(A7,$S$6:$U$17,3,FALSE) -> e3d | S7: 2 | T7: s3p3v3_d | U7: d9d
A8: 1 | B8: ="vstacks_"&VLOOKUP(A8,$S$6:$T$18,2,FALSE)&"~"&TEXT(O8,"0000") -> vstacks_s1p1v1_d~0003 | C8: =H8 -> c 2 deg (67%).e3d | H8: =_xlfn.TEXTJOIN(".",TRUE,I8:J8) -> c 2 deg (67%).e3d | I8: c 2 deg (67%) | J8: =Q8 -> e3d | L8: Limit warming to 2°C (>67%) with higher action post-2030 | O8: 3 | Q8: =VLOOKUP(A8,$S$6:$U$17,3,FALSE) -> e3d | S8: 3 | T8: s2_w | U8: b2w
A9: 1 | B9: ="vstacks_"&VLOOKUP(A9,$S$6:$T$18,2,FALSE)&"~"&TEXT(O9,"0000") -> vstacks_s1p1v1_d~0004 | C9: =H9 -> b 2 deg (50%).e3d | H9: =_xlfn.TEXTJOIN(".",TRUE,I9:J9) -> b 2 deg (50%).e3d | I9: b 2 deg (50%) | J9: =Q9 -> e3d | L9: Limit warming to 2°C (>50%) with immediate action | O9: 4 | Q9: =VLOOKUP(A9,$S$6:$U$17,3,FALSE) -> e3d | S9: 4 | T9: s2_w_p2_d | U9: a2w2d
A10: 1 | B10: ="vstacks_"&VLOOKUP(A10,$S$6:$T$18,2,FALSE)&"~"&TEXT(O10,"0000") -> vstacks_s1p1v1_d~0005 | C10: =H10 -> a 3 deg.e3d | H10: =_xlfn.TEXTJOIN(".",TRUE,I10:J10) -> a 3 deg.e3d | I10: a 3 deg | J10: =Q10 -> e3d | L10: Likely above 3°C warming with limited mitigation | O10: 5 | Q10: =VLOOKUP(A10,$S$6:$U$17,3,FALSE) -> e3d | S10: 5 | T10: ts12_clu | U10: hTS12c
A11: =A6+1 -> 2 | B11: ="vstacks_"&VLOOKUP(A11,$S$6:$T$18,2,FALSE)&"~"&TEXT(O11,"0000") -> vstacks_s3p3v3_d~0001 | C11: =H11 -> e 1.5 deg no OS.d9d | H11: =_xlfn.TEXTJOIN(".",TRUE,I11:J11) -> e 1.5 deg no OS.d9d | I11: =I6 -> e 1.5 deg no OS | J11: =Q11 -> d9d | O11: =O6 -> 1 | Q11: =VLOOKUP(A11,$S$6:$U$17,3,FALSE) -> d9d | S11: 6 | T11: ts24_clu | U11: gTS24c
A12: =A7+1 -> 2 | B12: ="vstacks_"&VLOOKUP(A12,$S$6:$T$18,2,FALSE)&"~"&TEXT(O12,"0000") -> vstacks_s3p3v3_d~0002 | C12: =H12 -> d 1.5 deg OS.d9d | H12: =_xlfn.TEXTJOIN(".",TRUE,I12:J12) -> d 1.5 deg OS.d9d | I12: =I7 -> d 1.5 deg OS | J12: =Q12 -> d9d | O12: =O7 -> 2 | Q12: =VLOOKUP(A12,$S$6:$U$17,3,FALSE) -> d9d | S12: 7 | T12: ts48_clu | U12: fTS48c
A13: =A8+1 -> 2 | B13: ="vstacks_"&VLOOKUP(A13,$S$6:$T$18,2,FALSE)&"~"&TEXT(O13,"0000") -> vstacks_s3p3v3_d~0003 | C13: =H13 -> c 2 deg (67%).d9d | H13: =_xlfn.TEXTJOIN(".",TRUE,I13:J13) -> c 2 deg (67%).d9d | I13: =I8 -> c 2 deg (67%) | J13: =Q13 -> d9d | O13: =O8 -> 3 | Q13: =VLOOKUP(A13,$S$6:$U$17,3,FALSE) -> d9d | S13: 8 | T13: s5p5v5_d | U13: c15d
A14: =A9+1 -> 2 | B14: ="vstacks_"&VLOOKUP(A14,$S$6:$T$18,2,FALSE)&"~"&TEXT(O14,"0000") -> vstacks_s3p3v3_d~0004 | C14: =H14 -> b 2 deg (50%).d9d | H14: =_xlfn.TEXTJOIN(".",TRUE,I14:J14) -> b 2 deg (50%).d9d | I14: =I9 -> b 2 deg (50%) | J14: =Q14 -> d9d | O14: =O9 -> 4 | Q14: =VLOOKUP(A14,$S$6:$U$17,3,FALSE) -> d9d | S14: 9 | T14: ts_12 | U14: iTS12
A15: =A10+1 -> 2 | B15: ="vstacks_"&VLOOKUP(A15,$S$6:$T$18,2,FALSE)&"~"&TEXT(O15,"0000") -> vstacks_s3p3v3_d~0005 | C15: =H15 -> a 3 deg.d9d | H15: =_xlfn.TEXTJOIN(".",TRUE,I15:J15) -> a 3 deg.d9d | I15: =I10 -> a 3 deg | J15: =Q15 -> d9d | O15: =O10 -> 5 | Q15: =VLOOKUP(A15,$S$6:$U$17,3,FALSE) -> d9d | S15: 10 | T15: ts_annual | U15: jAnn
A16: =A11+1 -> 3 | B16: ="vstacks_"&VLOOKUP(A16,$S$6:$T$18,2,FALSE)&"~"&TEXT(O16,"0000") -> vstacks_s2_w~0001 | C16: =H16 -> e 1.5 deg no OS.b2w | H16: =_xlfn.TEXTJOIN(".",TRUE,I16:J16) -> e 1.5 deg no OS.b2w | I16: =I11 -> e 1.5 deg no OS | J16: =Q16 -> b2w | O16: =O11 -> 1 | Q16: =VLOOKUP(A16,$S$6:$U$17,3,FALSE) -> b2w | S16: 11 | T16: s1_d | U16: f3d
A17: =A12+1 -> 3 | B17: ="vstacks_"&VLOOKUP(A17,$S$6:$T$18,2,FALSE)&"~"&TEXT(O17,"0000") -> vstacks_s2_w~0002 | C17: =H17 -> d 1.5 deg OS.b2w | H17: =_xlfn.TEXTJOIN(".",TRUE,I17:J17) -> d 1.5 deg OS.b2w | I17: =I12 -> d 1.5 deg OS | J17: =Q17 -> b2w | O17: =O12 -> 2 | Q17: =VLOOKUP(A17,$S$6:$U$17,3,FALSE) -> b2w
A18: =A13+1 -> 3 | B18: ="vstacks_"&VLOOKUP(A18,$S$6:$T$18,2,FALSE)&"~"&TEXT(O18,"0000") -> vstacks_s2_w~0003 | C18: =H18 -> c 2 deg (67%).b2w | H18: =_xlfn.TEXTJOIN(".",TRUE,I18:J18) -> c 2 deg (67%).b2w | I18: =I13 -> c 2 deg (67%) | J18: =Q18 -> b2w | O18: =O13 -> 3 | Q18: =VLOOKUP(A18,$S$6:$U$17,3,FALSE) -> b2w
A19: =A14+1 -> 3 | B19: ="vstacks_"&VLOOKUP(A19,$S$6:$T$18,2,FALSE)&"~"&TEXT(O19,"0000") -> vstacks_s2_w~0004 | C19: =H19 -> b 2 deg (50%).b2w | H19: =_xlfn.TEXTJOIN(".",TRUE,I19:J19) -> b 2 deg (50%).b2w | I19: =I14 -> b 2 deg (50%) | J19: =Q19 -> b2w | O19: =O14 -> 4 | Q19: =VLOOKUP(A19,$S$6:$U$17,3,FALSE) -> b2w
A20: =A15+1 -> 3 | B20: ="vstacks_"&VLOOKUP(A20,$S$6:$T$18,2,FALSE)&"~"&TEXT(O20,"0000") -> vstacks_s2_w~0005 | C20: =H20 -> a 3 deg.b2w | H20: =_xlfn.TEXTJOIN(".",TRUE,I20:J20) -> a 3 deg.b2w | I20: =I15 -> a 3 deg | J20: =Q20 -> b2w | O20: =O15 -> 5 | Q20: =VLOOKUP(A20,$S$6:$U$17,3,FALSE) -> b2w
A21: =A16+1 -> 4 | B21: ="vstacks_"&VLOOKUP(A21,$S$6:$T$18,2,FALSE)&"~"&TEXT(O21,"0000") -> vstacks_s2_w_p2_d~0001 | C21: =H21 -> e 1.5 deg no OS.a2w2d | H21: =_xlfn.TEXTJOIN(".",TRUE,I21:J21) -> e 1.5 deg no OS.a2w2d | I21: =I16 -> e 1.5 deg no OS | J21: =Q21 -> a2w2d | O21: =O16 -> 1 | Q21: =VLOOKUP(A21,$S$6:$U$17,3,FALSE) -> a2w2d
A22: =A17+1 -> 4 | B22: ="vstacks_"&VLOOKUP(A22,$S$6:$T$18,2,FALSE)&"~"&TEXT(O22,"0000") -> vstacks_s2_w_p2_d~0002 | C22: =H22 -> d 1.5 deg OS.a2w2d | H22: =_xlfn.TEXTJOIN(".",TRUE,I22:J22) -> d 1.5 deg OS.a2w2d | I22: =I17 -> d 1.5 deg OS | J22: =Q22 -> a2w2d | O22: =O17 -> 2 | Q22: =VLOOKUP(A22,$S$6:$U$17,3,FALSE) -> a2w2d
A23: =A18+1 -> 4 | B23: ="vstacks_"&VLOOKUP(A23,$S$6:$T$18,2,FALSE)&"~"&TEXT(O23,"0000") -> vstacks_s2_w_p2_d~0003 | C23: =H23 -> c 2 deg (67%).a2w2d | H23: =_xlfn.TEXTJOIN(".",TRUE,I23:J23) -> c 2 deg (67%).a2w2d | I23: =I18 -> c 2 deg (67%) | J23: =Q23 -> a2w2d | O23: =O18 -> 3 | Q23: =VLOOKUP(A23,$S$6:$U$17,3,FALSE) -> a2w2d
A24: =A19+1 -> 4 | B24: ="vstacks_"&VLOOKUP(A24,$S$6:$T$18,2,FALSE)&"~"&TEXT(O24,"0000") -> vstacks_s2_w_p2_d~0004 | C24: =H24 -> b 2 deg (50%).a2w2d | H24: =_xlfn.TEXTJOIN(".",TRUE,I24:J24) -> b 2 deg (50%).a2w2d | I24: =I19 -> b 2 deg (50%) | J24: =Q24 -> a2w2d | O24: =O19 -> 4 | Q24: =VLOOKUP(A24,$S$6:$U$17,3,FALSE) -> a2w2d
A25: =A20+1 -> 4 | B25: ="vstacks_"&VLOOKUP(A25,$S$6:$T$18,2,FALSE)&"~"&TEXT(O25,"0000") -> vstacks_s2_w_p2_d~0005 | C25: =H25 -> a 3 deg.a2w2d | H25: =_xlfn.TEXTJOIN(".",TRUE,I25:J25) -> a 3 deg.a2w2d | I25: =I20 -> a 3 deg | J25: =Q25 -> a2w2d | O25: =O20 -> 5 | Q25: =VLOOKUP(A25,$S$6:$U$17,3,FALSE) -> a2w2d
A26: =A21+1 -> 5 | B26: ="vstacks_"&VLOOKUP(A26,$S$6:$T$18,2,FALSE)&"~"&TEXT(O26,"0000") -> vstacks_ts12_clu~0001 | C26: =H26 -> e 1.5 deg no OS.hTS12c | H26: =_xlfn.TEXTJOIN(".",TRUE,I26:J26) -> e 1.5 deg no OS.hTS12c | I26: =I21 -> e 1.5 deg no OS | J26: =Q26 -> hTS12c | O26: =O21 -> 1 | Q26: =VLOOKUP(A26,$S$6:$U$17,3,FALSE) -> hTS12c
A27: =A22+1 -> 5 | B27: ="vstacks_"&VLOOKUP(A27,$S$6:$T$18,2,FALSE)&"~"&TEXT(O27,"0000") -> vstacks_ts12_clu~0002 | C27: =H27 -> d 1.5 deg OS.hTS12c | H27: =_xlfn.TEXTJOIN(".",TRUE,I27:J27) -> d 1.5 deg OS.hTS12c | I27: =I22 -> d 1.5 deg OS | J27: =Q27 -> hTS12c | O27: =O22 -> 2 | Q27: =VLOOKUP(A27,$S$6:$U$17,3,FALSE) -> hTS12c
A28: =A23+1 -> 5 | B28: ="vstacks_"&VLOOKUP(A28,$S$6:$T$18,2,FALSE)&"~"&TEXT(O28,"0000") -> vstacks_ts12_clu~0003 | C28: =H28 -> c 2 deg (67%).hTS12c | H28: =_xlfn.TEXTJOIN(".",TRUE,I28:J28) -> c 2 deg (67%).hTS12c | I28: =I23 -> c 2 deg (67%) | J28: =Q28 -> hTS12c | O28: =O23 -> 3 | Q28: =VLOOKUP(A28,$S$6:$U$17,3,FALSE) -> hTS12c
... A60: =A55+1 -> 11 | B60: ="vstacks_"&VLOOKUP(A60,$S$6:$T$18,2,FALSE)&"~"&TEXT(O60,"0000") -> vstacks_s1_d~0005 | C60: =H60 -> a 3 deg.f3d | H60: =_xlfn.TEXTJOIN(".",TRUE,I60:J60) -> a 3 deg.f3d | I60: =I55 -> a 3 deg | J60: =Q60 -> f3d | O60: =O55 -> 5 | Q60: =VLOOKUP(A60,$S$6:$U$17,3,FALSE) -> f3d

Sheet ScenMap
I1: C
I2: ar6_r10 | J2: timeslice
B4: ~ScenMap | H4: ~ScenG | O4: ~Scenmap
B5: Oname | C5: Name | D5: Desc | E5: Ldesc | H5: Scen | I5: ="sg_"&I2 -> sg_ar6_r10 | J5: ="sg_"&J2 -> sg_timeslice | N5: priority | O5: scen | P5: case_no | Q5: timeslice | R5: climate
B6: ="vs~"&TEXT(P6,"0000") -> vs~0001 | C6: =H6 -> e 1.5 deg no OS.kAnn | H6: =_xlfn.TEXTJOIN(".",TRUE,I6:J6) -> e 1.5 deg no OS.kAnn | I6: =VLOOKUP(R6,$W$6:$X$12,2,FALSE) -> e 1.5 deg no OS | J6: =VLOOKUP(Q6,$T$6:$U$20,2,FALSE) -> kAnn | L6: Limit warming to 1.5°C (>50%) with no or limited overshoot | N6: 5 | O6: e 1.5 deg no OS.kAnn | P6: 1 | Q6: ts_annual | R6: C1 | T6: ts_annual | U6: kAnn | W6: C1 | X6: e 1.5 deg no OS
B7: ="vs~"&TEXT(P7,"0000") -> vs~0002 | C7: =H7 -> d 1.5 deg OS.kAnn | H7: =_xlfn.TEXTJOIN(".",TRUE,I7:J7) -> d 1.5 deg OS.kAnn | I7: =VLOOKUP(R7,$W$6:$X$12,2,FALSE) -> d 1.5 deg OS | J7: =VLOOKUP(Q7,$T$6:$U$20,2,FALSE) -> kAnn | L7: Limit warming to 1.5°C (>67%) with high overshoot | N7: 5 | O7: d 1.5 deg OS.kAnn | P7: 2 | Q7: ts_annual | R7: C2 | T7: ts_12t | U7: k12 | W7: C2 | X7: d 1.5 deg OS
B8: ="vs~"&TEXT(P8,"0000") -> vs~0003 | C8: =H8 -> c 2 deg (67%).kAnn | H8: =_xlfn.TEXTJOIN(".",TRUE,I8:J8) -> c 2 deg (67%).kAnn | I8: =VLOOKUP(R8,$W$6:$X$12,2,FALSE) -> c 2 deg (67%) | J8: =VLOOKUP(Q8,$T$6:$U$20,2,FALSE) -> kAnn | L8: Limit warming to 2°C (>67%) with higher action post-2030 | N8: 5 | O8: c 2 deg (67%).kAnn | P8: 3 | Q8: ts_annual | R8: C3 | T8: ts_012 | U8: j12 | W8: C3 | X8: c 2 deg (67%)
B9: ="vs~"&TEXT(P9,"0000") -> vs~0004 | C9: =H9 -> b 2 deg (50%).kAnn | H9: =_xlfn.TEXTJOIN(".",TRUE,I9:J9) -> b 2 deg (50%).kAnn | I9: =VLOOKUP(R9,$W$6:$X$12,2,FALSE) -> b 2 deg (50%) | J9: =VLOOKUP(Q9,$T$6:$U$20,2,FALSE) -> kAnn | L9: Limit warming to 2°C (>50%) with immediate action | N9: 5 | O9: b 2 deg (50%).kAnn | P9: 4 | Q9: ts_annual | R9: C4 | T9: ts_024 | U9: i24 | W9: C4 | X9: b 2 deg (50%)
B10: ="vs~"&TEXT(P10,"0000") -> vs~0005 | C10: =H10 -> a 3 deg.kAnn | H10: =_xlfn.TEXTJOIN(".",TRUE,I10:J10) -> a 3 deg.kAnn | I10: =VLOOKUP(R10,$W$6:$X$12,2,FALSE) -> a 3 deg | J10: =VLOOKUP(Q10,$T$6:$U$20,2,FALSE) -> kAnn | L10: Likely above 3°C warming with limited mitigation | N10: 5 | O10: a 3 deg.kAnn | P10: 5 | Q10: ts_annual | R10: C7 | T10: ts_048 | U10: h48 | W10: C7 | X10: a 3 deg
B11: ="vs~"&TEXT(P11,"0000") -> vs~0006 | C11: =H11 -> e 1.5 deg no OS.k12 | H11: =_xlfn.TEXTJOIN(".",TRUE,I11:J11) -> e 1.5 deg no OS.k12 | I11: =VLOOKUP(R11,$W$6:$X$12,2,FALSE) -> e 1.5 deg no OS | J11: =VLOOKUP(Q11,$T$6:$U$20,2,FALSE) -> k12 | N11: 5 | O11: e 1.5 deg no OS.k12 | P11: 6 | Q11: ts_12t | R11: C1 | T11: ts_064 | U11: g64
B12: ="vs~"&TEXT(P12,"0000") -> vs~0007 | C12: =H12 -> d 1.5 deg OS.k12 | H12: =_xlfn.TEXTJOIN(".",TRUE,I12:J12) -> d 1.5 deg OS.k12 | I12: =VLOOKUP(R12,$W$6:$X$12,2,FALSE) -> d 1.5 deg OS | J12: =VLOOKUP(Q12,$T$6:$U$20,2,FALSE) -> k12 | N12: 5 | O12: d 1.5 deg OS.k12 | P12: 7 | Q12: ts_12t | R12: C2 | T12: ts_096P50 | U12: f96p50
B13: ="vs~"&TEXT(P13,"0000") -> vs~0008 | C13: =H13 -> c 2 deg (67%).k12 | H13: =_xlfn.TEXTJOIN(".",TRUE,I13:J13) -> c 2 deg (67%).k12 | I13: =VLOOKUP(R13,$W$6:$X$12,2,FALSE) -> c 2 deg (67%) | J13: =VLOOKUP(Q13,$T$6:$U$20,2,FALSE) -> k12 | N13: 5 | O13: c 2 deg (67%).k12 | P13: 8 | Q13: ts_12t | R13: C3 | T13: ts_096P10 | U13: f96p10
B14: ="vs~"&TEXT(P14,"0000") -> vs~0009 | C14: =H14 -> b 2 deg (50%).k12 | H14: =_xlfn.TEXTJOIN(".",TRUE,I14:J14) -> b 2 deg (50%).k12 | I14: =VLOOKUP(R14,$W$6:$X$12,2,FALSE) -> b 2 deg (50%) | J14: =VLOOKUP(Q14,$T$6:$U$20,2,FALSE) -> k12 | N14: 5 | O14: b 2 deg (50%).k12 | P14: 9 | Q14: ts_12t | R14: C4 | T14: ts_096P90 | U14: f96p90
B15: ="vs~"&TEXT(P15,"0000") -> vs~0010 | C15: =H15 -> a 3 deg.k12 | H15: =_xlfn.TEXTJOIN(".",TRUE,I15:J15) -> a 3 deg.k12 | I15: =VLOOKUP(R15,$W$6:$X$12,2,FALSE) -> a 3 deg | J15: =VLOOKUP(Q15,$T$6:$U$20,2,FALSE) -> k12 | N15: 5 | O15: a 3 deg.k12 | P15: 10 | Q15: ts_12t | R15: C7 | T15: s1p1v1_d | U15: e3d
B16: ="vs~"&TEXT(P16,"0000") -> vs~0011 | C16: =H16 -> e 1.5 deg no OS.j12 | H16: =_xlfn.TEXTJOIN(".",TRUE,I16:J16) -> e 1.5 deg no OS.j12 | I16: =VLOOKUP(R16,$W$6:$X$12,2,FALSE) -> e 1.5 deg no OS | J16: =VLOOKUP(Q16,$T$6:$U$20,2,FALSE) -> j12 | N16: 5 | O16: e 1.5 deg no OS.j12 | P16: 11 | Q16: ts_012 | R16: C1 | T16: s3p3v3_d | U16: d9d
B17: ="vs~"&TEXT(P17,"0000") -> vs~0012 | C17: =H17 -> d 1.5 deg OS.j12 | H17: =_xlfn.TEXTJOIN(".",TRUE,I17:J17) -> d 1.5 deg OS.j12 | I17: =VLOOKUP(R17,$W$6:$X$12,2,FALSE) -> d 1.5 deg OS | J17: =VLOOKUP(Q17,$T$6:$U$20,2,FALSE) -> j12 | N17: 5 | O17: d 1.5 deg OS.j12 | P17: 12 | Q17: ts_012 | R17: C2 | T17: s5p5v5_d | U17: c15d
B18: ="vs~"&TEXT(P18,"0000") -> vs~0013 | C18: =H18 -> c 2 deg (67%).j12 | H18: =_xlfn.TEXTJOIN(".",TRUE,I18:J18) -> c 2 deg (67%).j12 | I18: =VLOOKUP(R18,$W$6:$X$12,2,FALSE) -> c 2 deg (67%) | J18: =VLOOKUP(Q18,$T$6:$U$20,2,FALSE) -> j12 | N18: 5 | O18: c 2 deg (67%).j12 | P18: 13 | Q18: ts_012 | R18: C3 | T18: s2_w | U18: b2w
B19: ="vs~"&TEXT(P19,"0000") -> vs~0014 | C19: =H19 -> b 2 deg (50%).j12 | H19: =_xlfn.TEXTJOIN(".",TRUE,I19:J19) -> b 2 deg (50%).j12 | I19: =VLOOKUP(R19,$W$6:$X$12,2,FALSE) -> b 2 deg (50%) | J19: =VLOOKUP(Q19,$T$6:$U$20,2,FALSE) -> j12 | N19: 5 | O19: b 2 deg (50%).j12 | P19: 14 | Q19: ts_012 | R19: C4 | T19: s2_w_p2_d | U19: a2w2d
B20: ="vs~"&TEXT(P20,"0000") -> vs~0015 | C20: =H20 -> a 3 deg.j12 | H20: =_xlfn.TEXTJOIN(".",TRUE,I20:J20) -> a 3 deg.j12 | I20: =VLOOKUP(R20,$W$6:$X$12,2,FALSE) -> a 3 deg | J20: =VLOOKUP(Q20,$T$6:$U$20,2,FALSE) -> j12 | N20: 5 | O20: a 3 deg.j12 | P20: 15 | Q20: ts_012 | R20: C7
B21: ="vs~"&TEXT(P21,"0000") -> vs~0016 | C21: =H21 -> e 1.5 deg no OS.i24 | H21: =_xlfn.TEXTJOIN(".",TRUE,I21:J21) -> e 1.5 deg no OS.i24 | I21: =VLOOKUP(R21,$W$6:$X$12,2,FALSE) -> e 1.5 deg no OS | J21: =VLOOKUP(Q21,$T$6:$U$20,2,FALSE) -> i24 | N21: 5 | O21: e 1.5 deg no OS.i24 | P21: 16 | Q21: ts_024 | R21: C1
B22: ="vs~"&TEXT(P22,"0000") -> vs~0017 | C22: =H22 -> d 1.5 deg OS.i24 | H22: =_xlfn.TEXTJOIN(".",TRUE,I22:J22) -> d 1.5 deg OS.i24 | I22: =VLOOKUP(R22,$W$6:$X$12,2,FALSE) -> d 1.5 deg OS | J22: =VLOOKUP(Q22,$T$6:$U$20,2,FALSE) -> i24 | N22: 5 | O22: d 1.5 deg OS.i24 | P22: 17 | Q22: ts_024 | R22: C2
B23: ="vs~"&TEXT(P23,"0000") -> vs~0018 | C23: =H23 -> c 2 deg (67%).i24 | H23: =_xlfn.TEXTJOIN(".",TRUE,I23:J23) -> c 2 deg (67%).i24 | I23: =VLOOKUP(R23,$W$6:$X$12,2,FALSE) -> c 2 deg (67%) | J23: =VLOOKUP(Q23,$T$6:$U$20,2,FALSE) -> i24 | N23: 5 | O23: c 2 deg (67%).i24 | P23: 18 | Q23: ts_024 | R23: C3
B24: ="vs~"&TEXT(P24,"0000") -> vs~0019 | C24: =H24 -> b 2 deg (50%).i24 | H24: =_xlfn.TEXTJOIN(".",TRUE,I24:J24) -> b 2 deg (50%).i24 | I24: =VLOOKUP(R24,$W$6:$X$12,2,FALSE) -> b 2 deg (50%) | J24: =VLOOKUP(Q24,$T$6:$U$20,2,FALSE) -> i24 | N24: 5 | O24: b 2 deg (50%).i24 | P24: 19 | Q24: ts_024 | R24: C4
B25: ="vs~"&TEXT(P25,"0000") -> vs~0020 | C25: =H25 -> a 3 deg.i24 | H25: =_xlfn.TEXTJOIN(".",TRUE,I25:J25) -> a 3 deg.i24 | I25: =VLOOKUP(R25,$W$6:$X$12,2,FALSE) -> a 3 deg | J25: =VLOOKUP(Q25,$T$6:$U$20,2,FALSE) -> i24 | N25: 5 | O25: a 3 deg.i24 | P25: 20 | Q25: ts_024 | R25: C7
B26: ="vs~"&TEXT(P26,"0000") -> vs~0021 | C26: =H26 -> e 1.5 deg no OS.h48 | H26: =_xlfn.TEXTJOIN(".",TRUE,I26:J26) -> e 1.5 deg no OS.h48 | I26: =VLOOKUP(R26,$W$6:$X$12,2,FALSE) -> e 1.5 deg no OS | J26: =VLOOKUP(Q26,$T$6:$U$20,2,FALSE) -> h48 | N26: 5 | O26: e 1.5 deg no OS.h48 | P26: 21 | Q26: ts_048 | R26: C1
B27: ="vs~"&TEXT(P27,"0000") -> vs~0022 | C27: =H27 -> d 1.5 deg OS.h48 | H27: =_xlfn.TEXTJOIN(".",TRUE,I27:J27) -> d 1.5 deg OS.h48 | I27: =VLOOKUP(R27,$W$6:$X$12,2,FALSE) -> d 1.5 deg OS | J27: =VLOOKUP(Q27,$T$6:$U$20,2,FALSE) -> h48 | N27: 5 | O27: d 1.5 deg OS.h48 | P27: 22 | Q27: ts_048 | R27: C2
B28: ="vs~"&TEXT(P28,"0000") -> vs~0023 | C28: =H28 -> c 2 deg (67%).h48 | H28: =_xlfn.TEXTJOIN(".",TRUE,I28:J28) -> c 2 deg (67%).h48 | I28: =VLOOKUP(R28,$W$6:$X$12,2,FALSE) -> c 2 deg (67%) | J28: =VLOOKUP(Q28,$T$6:$U$20,2,FALSE) -> h48 | N28: 5 | O28: c 2 deg (67%).h48 | P28: 23 | Q28: ts_048 | R28: C3
B29: ="vs~"&TEXT(P29,"0000") -> vs~0024 | C29: =H29 -> b 2 deg (50%).h48 | H29: =_xlfn.TEXTJOIN(".",TRUE,I29:J29) -> b 2 deg (50%).h48 | I29: =VLOOKUP(R29,$W$6:$X$12,2,FALSE) -> b 2 deg (50%) | J29: =VLOOKUP(Q29,$T$6:$U$20,2,FALSE) -> h48 | N29: 5 | O29: b 2 deg (50%).h48 | P29: 24 | Q29: ts_048 | R29: C4
B30: ="vs~"&TEXT(P30,"0000") -> vs~0025 | C30: =H30 -> a 3 deg.h48 | H30: =_xlfn.TEXTJOIN(".",TRUE,I30:J30) -> a 3 deg.h48 | I30: =VLOOKUP(R30,$W$6:$X$12,2,FALSE) -> a 3 deg | J30: =VLOOKUP(Q30,$T$6:$U$20,2,FALSE) -> h48 | N30: 5 | O30: a 3 deg.h48 | P30: 25 | Q30: ts_048 | R30: C7
B31: ="vs~"&TEXT(P31,"0000") -> vs~0026 | C31: =H31 -> e 1.5 deg no OS.g64 | H31: =_xlfn.TEXTJOIN(".",TRUE,I31:J31) -> e 1.5 deg no OS.g64 | I31: =VLOOKUP(R31,$W$6:$X$12,2,FALSE) -> e 1.5 deg no OS | J31: =VLOOKUP(Q31,$T$6:$U$20,2,FALSE) -> g64 | N31: 5 | O31: e 1.5 deg no OS.g64 | P31: 26 | Q31: ts_064 | R31: C1
... B75: ="vs~"&TEXT(P75,"0000") -> vs~0070 | C75: =H75 -> a 3 deg.a2w2d | H75: =_xlfn.TEXTJOIN(".",TRUE,I75:J75) -> a 3 deg.a2w2d | I75: =VLOOKUP(R75,$W$6:$X$12,2,FALSE) -> a 3 deg | J75: =VLOOKUP(Q75,$T$6:$U$20,2,FALSE) -> a2w2d | N75: 5 | O75: a 3 deg.a2w2d | P75: 70 | Q75: s2_w_p2_d | R75: C7

Sheet geolocation
B9: ~geolocation
B10: region | C10: lat | D10: lng
B11: p_w66098469 | C11: 36.62316 | D11: 138.80177
B12: p_w87538349 | C12: 34.164921 | D12: 133.95401
B13: p_w102958903 | C13: 34.302173 | D13: 133.8625
B14: p_w104173570 | C14: 37.316219 | D14: 141.02184
B15: p_w104391636 | C15: 37.141851 | D15: 140.72296
B16: p_w104530060 | C16: 36.65527 | D16: 139.91772
B17: p_w105298089 | C17: 35.865258 | D17: 140.4581
B18: p_w106076988 | C18: 38.604777 | D18: 140.84893
B19: p_w106309481 | C19: 37.359426 | D19: 140.96069
B20: p_w109834508 | C20: 34.402513 | D20: 135.58694
B21: p_w109850439 | C21: 34.213924 | D21: 135.50212
B22: p_w110682956 | C22: 34.984223 | D22: 135.3461
... B298: rez_wof_044 | C298: 35.254536 | D298: 140.24751

Sheet process_map_geo
B9: ~process_map | F9: ~process_map
B10: dimension | C10: description | D10: pset_set | F10: pset_set | G10: dimension | H10: description
B11: grid_node | C11: p_w66098469 | D11: p_w66098469 | F11: p_w66098469 | G11: admin_1 | H11: Gunma
B12: grid_node | C12: p_w87538349 | D12: p_w87538349 | F12: p_w87538349 | G12: admin_1 | H12: Kagawa
B13: grid_node | C13: p_w102958903 | D13: p_w102958903 | F13: p_w102958903 | G13: admin_1 | H13: Kagawa
B14: grid_node | C14: p_w104173570 | D14: p_w104173570 | F14: p_w104173570 | G14: admin_1 | H14: Fukushima
B15: grid_node | C15: p_w104391636 | D15: p_w104391636 | F15: p_w104391636 | G15: admin_1 | H15: Fukushima
B16: grid_node | C16: p_w104530060 | D16: p_w104530060 | F16: p_w104530060 | G16: admin_1 | H16: Tochigi
B17: grid_node | C17: p_w105298089 | D17: p_w105298089 | F17: p_w105298089 | G17: admin_1 | H17: Chiba
B18: grid_node | C18: p_w106076988 | D18: p_w106076988 | F18: p_w106076988 | G18: admin_1 | H18: Miyagi
B19: grid_node | C19: p_w106309481 | D19: p_w106309481 | F19: p_w106309481 | G19: admin_1 | H19: Fukushima
B20: grid_node | C20: p_w109834508 | D20: p_w109834508 | F20: p_w109834508 | G20: admin_1 | H20: Ōsaka
B21: grid_node | C21: p_w109850439 | D21: p_w109850439 | F21: p_w109850439 | G21: admin_1 | H21: Wakayama
... B298: grid_node | C298: rez_wof_044 | D298: rez_wof_044 | F298: rez_wof_044 | G298: admin_1 | H298: Chiba

Sheet TS_Defs
A1: ~TS_Defs
A2: Attribute | B2: WAttribute | C2: PSET_Set | D2: PSET_PN | E2: PSET_PD | F2: PSET_CI | G2: PSET_CO | H2: CSET_Set | I2: CSET_CN | J2: CSET_CD | K2: Unit | L2: TS | M2: UC_N | N2: Name | O2: Desc | P2: Ldesc | Q2: show_me | R2: discard
A3: VAR_CAP | C3: ELE,STG,IRE | D3: -ElcAgg*,-*EV*,-g[_]* | K3: GW | N3: Elec Capacity
A4: VAR_NCAP | C4: ELE,STG,IRE | D4: -ElcAgg*,-*EV*,-g[_]* | K4: GW | N4: Elec New Capacity | T4: group_by
A5: VAR_FOUT | C5: ELE,IRE | D5: -ElcAgg*,-*EV*,-g[_]* | I5: ELC,ELC_???[_]???*,e[_]* | K5: Twh | N5: Elec Production | T5: p | U5: process
A6: VAR_POUT | C6: ELE,STG,IRE,-Grid | H6: NRG | I6: -elc_roadtransport | K6: Twh2GW | N6: Power | Q6: t
A7: VAR_FOUT | I7: CO2 | K7: kt | N7: CO2_emission
A8: VAR_FOUT | I8: CO2Captured | K8: ktneg | N8: CO2_captured
A9: Cost_INV | C9: ELE,STG,IRE | D9: -ElcAgg*,-*EV* | K9: m$2020 | N9: Cost_Investment
A10: EQ_COMBALM | B10: VAR_COMPRD | H10: NRG | K10: $/Mwh | N10: Price_NRG | P10: Prices of all NRG - native TS | Q10: ct
A11: EQ_COMBALM | B11: VAR_COMPRD | I11: co2net | K11: 000$/t | N11: Price_CO2
A12: User_conFXM | K12: m$/UCU | N12: UC_shadowprice | P12: shadow prices of all Ucs | Q12: u
A13: VAR_NCAPR | B13: VAR_NCAP | K13: $/Mwh | N13: LCOE | Q13: p
A14: Reg_wobj | K14: m$2020 | N14: SysCost_NPV | Q14: u
A15: Reg_ACost | K15: m$2020 | N15: SysCost_Annual | Q15: u
A16: VAR_CAP | C16: IRE | D16: g[_]* | K16: GW | N16: Grid Capacity
A17: VAR_NCAP | C17: IRE | D17: g[_]* | K17: GW | N17: Grid New Capacity
A18: VAR_FIN | D18: e_dem*,ev_bat*,H2Prd* | I18: e* | K18: Twh | N18: Demand

Sheet TS_ratios
C1: ~TS_Ratios
C2: var_num | D2: var_den | E2: Name | F2: Unit | G2: show_me | H2: ignore | I2: include_null | J2: include_dim | K2: Ldesc
C3: Elec Production | D3: Elec Capacity | E3: Capacity_factor | F3: Twh/GW | G3: p | I3: y | J3: p

Sheet Sankey
A3: DeACT TS_Defs: Snk_attr=SANKEY Grid Flows
A4: Attribute | B4: PSET_Set | C4: PSET_PN | D4: PSET_PD | E4: PSET_CI | F4: PSET_CO | G4: CSET_Set | H4: CSET_CN | I4: CSET_CD | J4: Unit | K4: TS | L4: UC_N | M4: Name | N4: Desc | O4: Ldesc | P4: show_me | Q4: ignore | R4: T_neg_andor | S4: downscale_option
A5: VAR_FOUT | B5: =_xlfn.TEXTJOIN(",",TRUE,PSet_MAP!$A$3:$A$49) -> CCGT,Int Comb,Gas_Oil Steam,OCGT (Peaker),Subcritical Coal,Supercritical Coal,IGCC,Bio Power,Solar Util,Wind onshore,Wind offshore,Geothermal P,Hydro Dam,Hydro RoR,Nuclear P,Nuclear SMR,Hydro pumped stg,Util Batt Stg,EV Batt,Demand,Transformers Dn,Transformers Up,Grid-220V,Grid-400V,Grid-380V,Grid-225V,Grid-330V,Grid-275V,Grid-420V,Grid-300V,Grid-500V,Grid-750V,Grid-450V,Grid-515V,Grid-525V,Grid-320V,Grid-150V,Grid-270V,Grid-350V,Grid-250V,Grid-200V,Grid-236V,Grid-600V,Aggregators,DUMMY_IMP | G5: =_xlfn.TEXTJOIN(",",TRUE,CSET_MAP!$A$3:$A$43) -> Elec-220V,Elec-400V,Elec-380V,Elec-225V,Elec-330V,Elec-275V,Elec-420V,Elec-300V,Elec-500V,Elec-750V,Elec-450V,Elec-515V,Elec-525V,Elec-320V,Elec-150V,Elec-270V,Elec-350V,Elec-250V,Elec-200V,Elec-236V,Elec-600V,Solar elec,Wind elec,hydrogen,ELC,buildings,industry,transport,EVs,fossil,renewable,bioenergy,nuclear | J5: TWh | M5: <cset>_Src_<pset> | S5: -1
A6: VAR_FIN | B6: =_xlfn.TEXTJOIN(",",TRUE,PSet_MAP!$A$3:$A$49) -> CCGT,Int Comb,Gas_Oil Steam,OCGT (Peaker),Subcritical Coal,Supercritical Coal,IGCC,Bio Power,Solar Util,Wind onshore,Wind offshore,Geothermal P,Hydro Dam,Hydro RoR,Nuclear P,Nuclear SMR,Hydro pumped stg,Util Batt Stg,EV Batt,Demand,Transformers Dn,Transformers Up,Grid-220V,Grid-400V,Grid-380V,Grid-225V,Grid-330V,Grid-275V,Grid-420V,Grid-300V,Grid-500V,Grid-750V,Grid-450V,Grid-515V,Grid-525V,Grid-320V,Grid-150V,Grid-270V,Grid-350V,Grid-250V,Grid-200V,Grid-236V,Grid-600V,Aggregators,DUMMY_IMP | G6: =_xlfn.TEXTJOIN(",",TRUE,CSET_MAP!$A$3:$A$43) -> Elec-220V,Elec-400V,Elec-380V,Elec-225V,Elec-330V,Elec-275V,Elec-420V,Elec-300V,Elec-500V,Elec-750V,Elec-450V,Elec-515V,Elec-525V,Elec-320V,Elec-150V,Elec-270V,Elec-350V,Elec-250V,Elec-200V,Elec-236V,Elec-600V,Solar elec,Wind elec,hydrogen,ELC,buildings,industry,transport,EVs,fossil,renewable,bioenergy,nuclear | J6: TWh | M6: <cset>_Snk_<pset> | S6: -1
A10: ~TS_Defs: Snk_attr=SANKEY whole system
A11: Attribute | B11: PSET_Set | C11: PSET_PN | D11: PSET_PD | E11: PSET_CI | F11: PSET_CO | G11: CSET_Set | H11: CSET_CN | I11: CSET_CD | J11: Unit | K11: TS | L11: UC_N | M11: Name | N11: Desc | O11: Ldesc | P11: show_me | Q11: ignore | R11: T_neg_andor | S11: downscale_option
A12: * | B12: Fuels
A13: VAR_FOUT | F13: =H13 -> bioenergy,coal,gas,geothermal,hydro,hydrogen,nuclear,oil,solar,windon,windoff | H13: =_xlfn.TEXTJOIN(",",TRUE,CName_MAP!$A$3:$A$16) -> bioenergy,coal,gas,geothermal,hydro,hydrogen,nuclear,oil,solar,windon,windoff | J13: TWh | M13: <gen_cname>_src_<gen_pname> | S13: -1
A14: VAR_FIN | B14: =B5 -> CCGT,Int Comb,Gas_Oil Steam,OCGT (Peaker),Subcritical Coal,Supercritical Coal,IGCC,Bio Power,Solar Util,Wind onshore,Wind offshore,Geothermal P,Hydro Dam,Hydro RoR,Nuclear P,Nuclear SMR,Hydro pumped stg,Util Batt Stg,EV Batt,Demand,Transformers Dn,Transformers Up,Grid-220V,Grid-400V,Grid-380V,Grid-225V,Grid-330V,Grid-275V,Grid-420V,Grid-300V,Grid-500V,Grid-750V,Grid-450V,Grid-515V,Grid-525V,Grid-320V,Grid-150V,Grid-270V,Grid-350V,Grid-250V,Grid-200V,Grid-236V,Grid-600V,Aggregators,DUMMY_IMP | H14: =_xlfn.TEXTJOIN(",",TRUE,CName_MAP!$A$3:$A$16) -> bioenergy,coal,gas,geothermal,hydro,hydrogen,nuclear,oil,solar,windon,windoff | J14: TWh | M14: <gen_cname>_snk_<pset> | S14: -1
A15: * | B15: Electricity
A16: VAR_FOUT | B16: =_xlfn.TEXTJOIN(",",TRUE,PSet_MAP!$A$3:$A$49) -> CCGT,Int Comb,Gas_Oil Steam,OCGT (Peaker),Subcritical Coal,Supercritical Coal,IGCC,Bio Power,Solar Util,Wind onshore,Wind offshore,Geothermal P,Hydro Dam,Hydro RoR,Nuclear P,Nuclear SMR,Hydro pumped stg,Util Batt Stg,EV Batt,Demand,Transformers Dn,Transformers Up,Grid-220V,Grid-400V,Grid-380V,Grid-225V,Grid-330V,Grid-275V,Grid-420V,Grid-300V,Grid-500V,Grid-750V,Grid-450V,Grid-515V,Grid-525V,Grid-320V,Grid-150V,Grid-270V,Grid-350V,Grid-250V,Grid-200V,Grid-236V,Grid-600V,Aggregators,DUMMY_IMP | G16: =_xlfn.TEXTJOIN(",",TRUE,CSET_MAP!$A$3:$A$31) -> Elec-220V,Elec-400V,Elec-380V,Elec-225V,Elec-330V,Elec-275V,Elec-420V,Elec-300V,Elec-500V,Elec-750V,Elec-450V,Elec-515V,Elec-525V,Elec-320V,Elec-150V,Elec-270V,Elec-350V,Elec-250V,Elec-200V,Elec-236V,Elec-600V,Solar elec,Wind elec,hydrogen,ELC,buildings,industry,transport,EVs | J16: TWh | M16: <cset>_src_<pset> | S16: -1
A17: VAR_FIN | B17: =_xlfn.TEXTJOIN(",",TRUE,PSet_MAP!$A$3:$A$49) -> CCGT,Int Comb,Gas_Oil Steam,OCGT (Peaker),Subcritical Coal,Supercritical Coal,IGCC,Bio Power,Solar Util,Wind onshore,Wind offshore,Geothermal P,Hydro Dam,Hydro RoR,Nuclear P,Nuclear SMR,Hydro pumped stg,Util Batt Stg,EV Batt,Demand,Transformers Dn,Transformers Up,Grid-220V,Grid-400V,Grid-380V,Grid-225V,Grid-330V,Grid-275V,Grid-420V,Grid-300V,Grid-500V,Grid-750V,Grid-450V,Grid-515V,Grid-525V,Grid-320V,Grid-150V,Grid-270V,Grid-350V,Grid-250V,Grid-200V,Grid-236V,Grid-600V,Aggregators,DUMMY_IMP | G17: =_xlfn.TEXTJOIN(",",TRUE,CSET_MAP!$A$3:$A$31) -> Elec-220V,Elec-400V,Elec-380V,Elec-225V,Elec-330V,Elec-275V,Elec-420V,Elec-300V,Elec-500V,Elec-750V,Elec-450V,Elec-515V,Elec-525V,Elec-320V,Elec-150V,Elec-270V,Elec-350V,Elec-250V,Elec-200V,Elec-236V,Elec-600V,Solar elec,Wind elec,hydrogen,ELC,buildings,industry,transport,EVs | J17: TWh | M17: <cset>_snk_<pset> | S17: -1
A18: * | B18: Hydrogen
A19: VAR_FOUT | F19: =H19 -> hydrogen | H19: hydrogen | J19: TWh | M19: <gen_cname>_src_<gen_pname> | S19: -1
A20: VAR_FIN | F20: hydrogen | G20: =_xlfn.TEXTJOIN(",",TRUE,CSET_MAP!$A$3:$A$43) -> Elec-220V,Elec-400V,Elec-380V,Elec-225V,Elec-330V,Elec-275V,Elec-420V,Elec-300V,Elec-500V,Elec-750V,Elec-450V,Elec-515V,Elec-525V,Elec-320V,Elec-150V,Elec-270V,Elec-350V,Elec-250V,Elec-200V,Elec-236V,Elec-600V,Solar elec,Wind elec,hydrogen,ELC,buildings,industry,transport,EVs,fossil,renewable,bioenergy,nuclear | J20: TWh | M20: <cset>_snk_<gen_pname> | S20: -1
A23: VAR_FIN | E23: hydrogen | H23: hydrogen | J23: TWh | M23: <gen_cname>_snk_<gen_pname> | S23: -1

Sheet PSet_MAP
A1: ~Pset_Map
A2: Pset | B2: Desc | C2: Ldesc
A3: CCGT | B3: =A3 -> CCGT
A4: Int Comb | B4: =A4 -> Int Comb
A5: Gas_Oil Steam | B5: =A5 -> Gas_Oil Steam
A6: OCGT (Peaker) | B6: =A6 -> OCGT (Peaker)
A7: Subcritical Coal | B7: =A7 -> Subcritical Coal
A8: Supercritical Coal | B8: =A8 -> Supercritical Coal
A9: IGCC | B9: =A9 -> IGCC
A10: Bio Power | B10: =A10 -> Bio Power
A11: Solar Util | B11: =A11 -> Solar Util
A12: Wind onshore | B12: Onshore Wind
A13: Wind offshore | B13: Offshore Wind
A14: Geothermal P | B14: =A14 -> Geothermal P
A15: Hydro Dam | B15: =A15 -> Hydro Dam
A16: Hydro RoR | B16: =A16 -> Hydro RoR
A17: Nuclear P | B17: =A17 -> Nuclear P
A18: Nuclear SMR | B18: =A18 -> Nuclear SMR
A19: Hydro pumped stg | B19: =A19 -> Hydro pumped stg
A20: Util Batt Stg | B20: =A20 -> Util Batt Stg
A21: EV Batt | B21: =A21 -> EV Batt
A22: Demand | B22: =A22 -> Demand
A23: Transformers Dn | B23: =A23 -> Transformers Dn
A24: Transformers Up | B24: =A24 -> Transformers Up
A25: Grid-220V | B25: =A25 -> Grid-220V
... A47: DUMMY_IMP | B47: =A47 -> DUMMY_IMP

Sheet CSET_MAP
A1: ~Cset_Map
A2: Cset | B2: Desc | C2: Ldesc
A3: Elec-220V | B3: =A3 -> Elec-220V
A4: Elec-400V | B4: =A4 -> Elec-400V
A5: Elec-380V | B5: =A5 -> Elec-380V
A6: Elec-225V | B6: =A6 -> Elec-225V
A7: Elec-330V | B7: =A7 -> Elec-330V
A8: Elec-275V | B8: =A8 -> Elec-275V
A9: Elec-420V | B9: =A9 -> Elec-420V
A10: Elec-300V | B10: =A10 -> Elec-300V
A11: Elec-500V | B11: =A11 -> Elec-500V
A12: Elec-750V | B12: =A12 -> Elec-750V
A13: Elec-450V | B13: =A13 -> Elec-450V
A14: Elec-515V | B14: =A14 -> Elec-515V
... A23: Elec-600V | B23: =A23 -> Elec-600V
A24: Solar elec | B24: Electricity
A25: Wind elec | B25: Electricity
A26: hydrogen | B26: =A26 -> hydrogen
A27: ELC | B27: Electricity
A28: buildings | B28: =A28 -> buildings
A29: industry | B29: =A29 -> industry
A30: transport | B30: =A30 -> transport
A31: EVs | B31: =A31 -> EVs
A32: fossil | B32: =A32 -> fossil
A33: renewable | B33: =A33 -> renewable
A34: bioenergy | B34: =A34 -> bioenergy
A35: nuclear | B35: =A35 -> nuclear

Sheet CName_MAP
A1: ~CName_Map
A2: CName | B2: Desc | C2: Ldesc
A3: bioenergy | B3: =A3 -> bioenergy
A4: coal | B4: =A4 -> coal
A5: gas | B5: =A5 -> gas
A6: geothermal | B6: =A6 -> geothermal
A7: hydro | B7: =A7 -> hydro
A8: hydrogen | B8: =A8 -> hydrogen
A9: nuclear | B9: =A9 -> nuclear
A10: oil | B10: =A10 -> oil
A11: solar | B11: =A11 -> solar
A12: windon | B12: wind onshore
A13: windoff | B13: wind offshore

Sheet timeslice map
A1: ~Timeslice_Map
A2: dimension | B2: name | C2: description
A3: ts_type | B3: *,-s?a* | C3: hourly
A4: ts_type | B4: s?a* | C4: aggregated
A5: ts_season | B5: S1* | C5: =LEFT(B5,2) -> S1
A6: ts_season | B6: S2* | C6: =LEFT(B6,2) -> S2
A7: ts_season | B7: S3* | C7: =LEFT(B7,2) -> S3
A8: ts_season | B8: S4* | C8: =LEFT(B8,2) -> S4
A9: ts_season | B9: S5* | C9: =LEFT(B9,2) -> S5
A10: ts_season | B10: S6* | C10: =LEFT(B10,2) -> S6

Sheet process map
A1: ~process_map
A2: dimension | B2: name | C2: description | D2: pset_set | E2: pset_ci | F2: pset_co | G2: pset_pd
A3: old_new | B3: * | C3: new
A4: old_new | B4: ep* | C4: old
A5: Tech | C5: =D5 -> CCGT | D5: CCGT
A6: Tech | C6: =D6 -> Int Comb | D6: Int Comb
A7: Tech | C7: =D7 -> Gas_Oil Steam | D7: Gas_Oil Steam
A8: Tech | C8: =D8 -> OCGT (Peaker) | D8: OCGT (Peaker)
A9: Tech | C9: =D9 -> Subcritical Coal | D9: Subcritical Coal
A10: Tech | C10: =D10 -> Supercritical Coal | D10: Supercritical Coal
A11: Tech | C11: =D11 -> IGCC | D11: IGCC
A12: Tech | C12: =D12 -> Bio Power | D12: Bio Power
A13: Tech | C13: =D13 -> Solar Util | D13: Solar Util
A14: Tech | C14: =D14 -> Wind onshore | D14: Wind onshore
A15: Tech | C15: =D15 -> Wind offshore | D15: Wind offshore
A16: Tech | C16: =D16 -> Geothermal P | D16: Geothermal P
... A49: Tech | C49: =D49 -> DUMMY_IMP | D49: DUMMY_IMP
A50: Tech | B50: *ccs | C50: Coal CCS | E50: coal
A51: Tech | B51: *ccs | C51: Gas CCS | E51: gas
A52: Tech | B52: *ccs-rf | C52: Coal CCS Retrofit | E52: coal
A53: Tech | B53: *ccs-rf | C53: Gas CCS Retrofit | E53: gas
A54: Tech | B54: ElcAgg_Solar | C54: Solar
A55: Tech | B55: ElcAgg_Wind | C55: Wind
A56: Tech | B56: Trd* | C56: Trade
A57: Sector | B57: e_dem* | C57: Industry and Buildings
A58: Sector | B58: ev_bat* | C58: EV Batt
A59: Sector | B59: H2Prd* | C59: Hydrogen

Sheet commodity map
A1: ~commodity_map
A2: dimension | B2: name | C2: description | D2: cset_set | E2: cset_cd | F2: c_set_andor | G2: c_pos_andor | H2: c_neg_andor

Sheet ATS
A1: ~ATS
A2: Model | B2: Scen | C2: Region | D2: Varbl | E2: Unit | F2: Year | G2: Val

Sheet UnitConv
A1: ~UnitConv
A2: Model | B2: Unit1 | C2: Unit2 | D2: MultFact
A3: VS | B3: Twh2GW | C3: GW | D3: =1/8.76 -> 0.11415525
A4: VS | B4: Twh/GW | C4: % | D4: =1/8.76*100 -> 11.415525
A5: VS | B5: kt | C5: mt | D5: 0.001
A6: VS | B6: ktneg | C6: mt | D6: -0.001
A7: VS | B7: 000$/t | C7: $/tCO2 | D7: -1000
