Workbook
Name IQ_CH: 110000
Name IQ_CQ: 5000
Name IQ_CY: 10000
Name IQ_DAILY: 500000
Name IQ_FH: 100000
Name IQ_FQ: 500
Name IQ_FY: 1000
Name IQ_LTM: 2000
Name IQ_MONTH: 15000
Name IQ_NTM: 6000
Name IQ_WEEK: 50000
Name IQ_YTD: 3000

Sheet veda input
D2: ~TFM_INS-AT: limtype=UP; Curr=USD22 | N2: ~TFM_INS-AT: limtype=LO
B3: *technology | C3: *Size Class | D3: ACT_MINLD | E3: ACT_TIME | F3: ACT_UPS | G3: ACT_CSTUP | H3: pset_set | I3: attrib_cond | J3: val_cond | K3: pset_pd | L3: ncap_dcost | N3: ACT_TIME | O3: ACT_UPS | P3: pset_set | Q3: attrib_cond | R3: val_cond | S3: pset_pd
B4: OCGT (Peaker) | C4: >200 MW | D4: 0.35 | E4: 1.5 | F4: 0.8 | G4: 0.02 | H4: OCGT (Peaker) | K4: -aggregated* | L4: =dcost_data!C2 -> 50 | N4: 1.5 | O4: 0.8 | P4: =H4 -> OCGT (Peaker) | Q4: =IF(I4="","",I4) | R4: =IF(J4="","",J4) | S4: =IF(K4="","",K4) -> -aggregated*
B5: OCGT (Peaker) | C5: 50-200 MW | D5: 0.3 | E5: 1 | F5: 1 | G5: 0.015 | H5: OCGT (Peaker) | I5: PASTI | J5: <.2 | K5: -aggregated* | L5: =dcost_data!C3 -> 40 | N5: 1 | O5: 1 | P5: =H5 -> OCGT (Peaker) | Q5: =IF(I5="","",I5) -> PASTI | R5: =IF(J5="","",J5) -> <.2 | S5: =IF(K5="","",K5) -> -aggregated*
B6: OCGT (Peaker) | C6: <50 MW | D6: 0.25 | E6: 0.5 | F6: 1.2 | G6: 0.01 | H6: OCGT (Peaker) | I6: PASTI | J6: <.05 | K6: -aggregated* | L6: =dcost_data!C4 -> 30 | N6: 0.5 | O6: 1.2 | P6: =H6 -> OCGT (Peaker) | Q6: =IF(I6="","",I6) -> PASTI | R6: =IF(J6="","",J6) -> <.05 | S6: =IF(K6="","",K6) -> -aggregated*
B7: CCGT | C7: >300 MW | D7: 0.55 | E7: 4 | F7: 0.45 | G7: 0.04 | H7: CCGT | K7: -aggregated* | L7: =dcost_data!C5 -> 60 | N7: 4 | O7: 0.45 | P7: =H7 -> CCGT | Q7: =IF(I7="","",I7) | R7: =IF(J7="","",J7) | S7: =IF(K7="","",K7) -> -aggregated*
B8: CCGT | C8: <300 MW | D8: 0.5 | E8: 2 | F8: 0.6 | G8: 0.025 | H8: CCGT | I8: PASTI | J8: <.3 | K8: -aggregated* | L8: =dcost_data!C6 -> 50 | N8: 2 | O8: 0.6 | P8: =H8 -> CCGT | Q8: =IF(I8="","",I8) -> PASTI | R8: =IF(J8="","",J8) -> <.3 | S8: =IF(K8="","",K8) -> -aggregated*
B9: Gas/Oil Steam | C9: >200 MW | D9: 0.4 | E9: 5 | F9: 0.3 | G9: 0.035 | H9: Gas_Oil Steam | K9: -aggregated* | L9: =dcost_data!C7 -> 70 | N9: 5 | O9: 0.3 | P9: =H9 -> Gas_Oil Steam | Q9: =IF(I9="","",I9) | R9: =IF(J9="","",J9) | S9: =IF(K9="","",K9) -> -aggregated*
B10: Gas/Oil Steam | C10: <200 MW | D10: 0.35 | E10: 3 | F10: 0.4 | G10: 0.025 | H10: Gas_Oil Steam | I10: PASTI | J10: <.2 | K10: -aggregated* | L10: =dcost_data!C8 -> 60 | N10: 3 | O10: 0.4 | P10: =H10 -> Gas_Oil Steam | Q10: =IF(I10="","",I10) -> PASTI | R10: =IF(J10="","",J10) -> <.2 | S10: =IF(K10="","",K10) -> -aggregated*
B11: Diesel | C11: >20 MW | D11: 0.35 | E11: 2 | F11: 0.6 | G11: 0.02 | H11: Int Comb | K11: -aggregated* | L11: =dcost_data!C9 -> 40 | N11: 2 | O11: 0.6 | P11: =H11 -> Int Comb | Q11: =IF(I11="","",I11) | R11: =IF(J11="","",J11) | S11: =IF(K11="","",K11) -> -aggregated*
B12: Diesel | C12: <20 MW | D12: 0.3 | E12: 1 | F12: 1.2 | G12: 0.01 | H12: Int Comb | I12: PASTI | J12: <.02 | K12: -aggregated* | L12: =dcost_data!C10 -> 30 | N12: 1 | O12: 1.2 | P12: =H12 -> Int Comb | Q12: =IF(I12="","",I12) -> PASTI | R12: =IF(J12="","",J12) -> <.02 | S12: =IF(K12="","",K12) -> -aggregated*
B13: Subcritical Coal | C13: >300 MW | D13: 0.42 | E13: 7 | F13: 0.2 | G13: 0.06 | H13: Subcritical Coal, bioenergy | K13: -aggregated* | L13: =dcost_data!C11 -> 100 | N13: 7 | O13: 0.2 | P13: =H13 -> Subcritical Coal, bioenergy | Q13: =IF(I13="","",I13) | R13: =IF(J13="","",J13) | S13: =IF(K13="","",K13) -> -aggregated*
B14: Subcritical Coal | C14: <300 MW | D14: 0.38 | E14: 5 | F14: 0.3 | G14: 0.04 | H14: =H13 -> Subcritical Coal, bioenergy | I14: PASTI | J14: <.3 | K14: -aggregated* | L14: =dcost_data!C12 -> 90 | N14: 5 | O14: 0.3 | P14: =H14 -> Subcritical Coal, bioenergy | Q14: =IF(I14="","",I14) -> PASTI | R14: =IF(J14="","",J14) -> <.3 | S14: =IF(K14="","",K14) -> -aggregated*
B15: Supercritical Coal | C15: >500 MW | D15: 0.48 | E15: 8 | F15: 0.15 | G15: 0.07 | H15: Supercritical Coal, IGCC | K15: -aggregated* | L15: =dcost_data!C13 -> 110 | N15: 8 | O15: 0.15 | P15: =H15 -> Supercritical Coal, IGCC | Q15: =IF(I15="","",I15) | R15: =IF(J15="","",J15) | S15: =IF(K15="","",K15) -> -aggregated*
B16: Supercritical Coal | C16: <500 MW | D16: 0.45 | E16: 6 | F16: 0.25 | G16: 0.05 | H16: =H15 -> Supercritical Coal, IGCC | I16: PASTI | J16: <.5 | K16: -aggregated* | L16: =dcost_data!C14 -> 100 | N16: 6 | O16: 0.25 | P16: =H16 -> Supercritical Coal, IGCC | Q16: =IF(I16="","",I16) -> PASTI | R16: =IF(J16="","",J16) -> <.5 | S16: =IF(K16="","",K16) -> -aggregated*
B17: Nuclear | C17: All | D17: 0.7 | E17: 24 | F17: 0.05 | G17: 0.1 | H17: Nuclear P | K17: -aggregated* | L17: =dcost_data!C15 -> 500 | N17: 24 | O17: 0.05 | P17: =H17 -> Nuclear P | Q17: =IF(I17="","",I17) | R17: =IF(J17="","",J17) | S17: =IF(K17="","",K17) -> -aggregated*
B18: OCGT (Peaker) | C18: <50 MW | D18: 0 | E18: 0.5 | F18: 1.2 | G18: 0.01 | K18: Gas Turbine* | L18: 30 | N18: 0.5 | O18: 1.2 | S18: Gas Turbine*

Sheet Thermal elec op costs
B2: Fixom and Varom computation for NEEDS units.sql | AJ2: ~TFM_INS-TS: attribute=SHAPE
B3: Plant Type | C3: SO2 Control | D3: NOx Control | E3: Hg Control | F3: Age of Unit | G3: FOM (2019$ /kW-Yr) | H3: Age2 | I3: FOM2 | J3: SHAPE | K3: 1 | L3: 39 | M3: 40 | N3: 41 | O3: =N3+18 -> 59 | P3: =O3+1 -> 60 | Q3: =P3+1 -> 61 | R3: =Q3+18 -> 79 | S3: =R3+1 -> 80 | T3: =S3+1 -> 81 | U3: =T3+18 -> 99 | V3: =U3+1 -> 100 | W3: =V3+1 -> 101 | X3: =W3+18 -> 119 | Y3: =X3+1 -> 120 | Z3: =Y3+1 -> 121 | AA3: =Z3+18 -> 139 | AB3: =AA3+1 -> 140 | AC3: =AB3+1 -> 141 | AD3: =AC3+18 -> 159 | AE3: =AD3+1 -> 160 | AF3: =AE3+1 -> 161 | AG3: =AF3+18 -> 179 | AH3: =AG3+1 -> 180 | AJ3: other_indexes | AK3: =K3 -> 1 | AL3: =L3 -> 39 | AM3: =M3 -> 40 | AN3: =N3 -> 41 | AO3: =O3 -> 59 | AP3: =P3 -> 60 | AQ3: =Q3 -> 61 | AR3: =R3 -> 79 | ... BH3: =AH3 -> 180
B4: Coal Steam | C4: Dry FGD | D4: None | E4: None | F4: 0 to 40 Years | G4: 39.18 | H4: 40 to 50 Years | I4: 43.5 | J4: 81 | K4: 1 | L4: 1.11 | M4: 6.18 | N4: 1 | O4: 1.11 | P4: 6.18 | Q4: 1 | R4: 1.11 | S4: 6.18 | T4: 1 | U4: 1.11 | V4: 6.18 | W4: 1 | X4: 1.11 | Y4: 6.18 | Z4: =W4 -> 1 | AA4: =X4 -> 1.11 | AB4: =Y4 -> 6.18 | AC4: =Z4 -> 1 | AD4: =AA4 -> 1.11 | AE4: =AB4 -> 6.18 | AF4: =AC4 -> 1 | AG4: =AD4 -> 1.11 | AH4: =AE4 -> 6.18 | AJ4: =J4 -> 81 | AK4: =K4 -> 1 | AL4: =L4 -> 1.11 | AM4: =M4 -> 6.18 | AN4: =N4 -> 1 | AO4: =O4 -> 1.11 | AP4: =P4 -> 6.18 | AQ4: =Q4 -> 1 | ... BH4: =AH4 -> 6.18
B5: O/G Steam | C5: None | D5: SCR | E5: None | F5: 0 to 40 Years | G5: 19.34 | H5: 40 to 50 Years | I5: 28.67 | J5: 82 | K5: 1 | L5: 1.48 | M5: 10 | N5: 1 | O5: 1.48 | P5: 10 | Q5: 1 | R5: 1.48 | S5: 10 | T5: 1 | U5: 1.48 | V5: 10 | W5: 1 | X5: 1.48 | Y5: 10 | Z5: =W5 -> 1 | AA5: =X5 -> 1.48 | AB5: =Y5 -> 10 | AC5: =Z5 -> 1 | AD5: =AA5 -> 1.48 | AE5: =AB5 -> 10 | AF5: =AC5 -> 1 | AG5: =AD5 -> 1.48 | AH5: =AE5 -> 10 | AJ5: =J5 -> 82 | AK5: =K5 -> 1 | AL5: =L5 -> 1.48 | AM5: =M5 -> 10 | AN5: =N5 -> 1 | AO5: =O5 -> 1.48 | AP5: =P5 -> 10 | AQ5: =Q5 -> 1 | ... BH5: =AH5 -> 10
AJ7: ~TFM_INS-TS: attribute=SHAPE
B8: Plant Type | C8: SO2 Control | D8: NOx Control | E8: Hg Control | F8: Age of Unit | G8: FOM (2019$ /kW-Yr) | H8: SHAPE | I8: 1 | J8: 29 | K8: 30 | L8: 31 | M8: 59 | N8: 60 | O8: 61 | P8: 89 | Q8: 90 | R8: 91 | S8: 119 | T8: 120 | U8: 121 | V8: 149 | W8: 150 | X8: 151 | Y8: 179 | Z8: 180 | AA8: 181 | AB8: 200 | AJ8: other_indexes | AK8: =I8 -> 1 | AL8: =J8 -> 29 | AM8: =K8 -> 30 | AN8: =L8 -> 31 | AO8: =M8 -> 59 | AP8: =N8 -> 60 | AQ8: =O8 -> 61 | AR8: =P8 -> 89 | ... BD8: =AB8 -> 200
B9: Combined Cycle | C9: None | D9: None | E9: None | F9: All Years | G9: 30.18 | H9: 83 | I9: 1 | J9: 1 | K9: 3.72 | L9: 1 | M9: 1 | N9: 3.72 | O9: 1 | P9: 1 | Q9: 3.72 | R9: 1 | S9: 1 | T9: 3.72 | U9: 1 | V9: 1 | W9: 3.72 | X9: 1 | Y9: 1 | Z9: 3.72 | AA9: 1 | AB9: 3.72 | AJ9: =H9 -> 83 | AK9: =I9 -> 1 | AL9: =J9 -> 1 | AM9: =K9 -> 3.72 | AN9: =L9 -> 1 | AO9: =M9 -> 1 | AP9: =N9 -> 3.72 | AQ9: =O9 -> 1 | ... BD9: =AB9 -> 3.72
B10: Combustion Turbine | C10: None | D10: None | E10: None | F10: All Years | G10: 19.73 | H10: 84 | I10: 1 | J10: 1 | K10: 13.27 | L10: 1 | M10: 1 | N10: 13.27 | O10: 1 | P10: 1 | Q10: 13.27 | R10: 1 | S10: 1 | T10: 13.27 | U10: 1 | V10: 1 | W10: 13.27 | X10: 1 | Y10: 1 | Z10: 13.27 | AA10: 1 | AB10: 13.27 | AJ10: =H10 -> 84 | AK10: =I10 -> 1 | AL10: =J10 -> 1 | AM10: =K10 -> 13.27 | AN10: =L10 -> 1 | AO10: =M10 -> 1 | AP10: =N10 -> 13.27 | AQ10: =O10 -> 1 | ... BD10: =AB10 -> 13.27
B13: IPM Table 4-10 Life Extension Cost Assumptions Used in v6
B14: The life extension costs were added once the unit reaches its assumed lifespan.
B15: However, if the unit reaches its lifespan before the first run year, then the life extension cost was applied when the unit reaches twice its lifespan age.
B16: The assumption implies if the unit has reached its lifespan before the first run year, it has already incurred the necessary life extension related investment costs and is considered sunk.
B18: Type, Lifespan | C18: Lifespan | D18: Life Extension Cost (2019$/kW)
B19: Biomass 40 | C19: 40 | D19: 253
B20: Coal Steam 40 | C20: 40 | D20: 203 | H20: ~TFM_INS-TS
B21: Combined Cycle 30 | C21: 30 | D21: 82 | H21: attribute | I21: PSET_SET | J21: PSET_CI | K21: 2019 | L21: 0
B22: Combustion Turbine 30 | C22: 30 | D22: 242 | H22: NCAP_FOMX | I22: ELE | J22: coal | K22: =AJ4 -> 81 | L22: 2
B23: IC Engine 30 | C23: 30 | D23: 226 | H23: NCAP_FOMX | I23: Gas_Oil Steam | K23: =AJ5 -> 82 | L23: 2
B24: Oil/Gas Steam 40 | C24: 40 | D24: 174 | H24: NCAP_FOMX | I24: CCGT | K24: =AJ9 -> 83 | L24: 2
B25: IGCC 40 | C25: 40 | D25: 258 | H25: NCAP_FOMX | I25: OCGT (Peaker) | K25: =AJ10 -> 84 | L25: 2
B26: Landfill Gas 20 | C26: 20 | D26: 135

Sheet uc_data
B2: technology | C2: Size Class | D2: Min Stable Factor (%) | E2: Min Up Time (h) | F2: Min Down Time (h) | G2: Max Ramp Up (%/h) | H2: Max Ramp Down (%/h) | I2: Startup Time (h) | J2: Startup Cost ($/MW) | K2: Shutdown Cost ($/MW)
B3: OCGT (Peaker) | C3: <50 MW | D3: 25 | E3: 0.5 | F3: 0.5 | G3: 120 | H3: 120 | I3: 0.5 | J3: 10 | K3: 2
B4: OCGT (Peaker) | C4: 50-200 MW | D4: 30 | E4: 1 | F4: 1 | G4: 100 | H4: 100 | I4: 0.75 | J4: 15 | K4: 4
B5: OCGT (Peaker) | C5: >200 MW | D5: 35 | E5: 1.5 | F5: 1.5 | G5: 80 | H5: 80 | I5: 1.25 | J5: 20 | K5: 6
B6: CCGT | C6: <300 MW | D6: 50 | E6: 2 | F6: 2 | G6: 60 | H6: 60 | I6: 1.75 | J6: 25 | K6: 6
B7: CCGT | C7: >300 MW | D7: 55 | E7: 4 | F7: 4 | G7: 45 | H7: 45 | I7: 3 | J7: 40 | K7: 9
B8: Gas/Oil Steam | C8: <200 MW | D8: 35 | E8: 3 | F8: 3 | G8: 40 | H8: 40 | I8: 2 | J8: 25 | K8: 5
B9: Gas/Oil Steam | C9: >200 MW | D9: 40 | E9: 5 | F9: 5 | G9: 30 | H9: 30 | I9: 3 | J9: 35 | K9: 7
B10: Diesel | C10: <20 MW | D10: 30 | E10: 1 | F10: 1 | G10: 120 | H10: 120 | I10: 0.4 | J10: 10 | K10: 2
B11: Diesel | C11: >20 MW | D11: 35 | E11: 2 | F11: 2 | G11: 60 | H11: 60 | I11: 1.5 | J11: 20 | K11: 6
B12: Subcritical Coal | C12: <300 MW | D12: 38 | E12: 5 | F12: 5 | G12: 30 | H12: 30 | I12: 5 | J12: 40 | K12: 10
B13: Subcritical Coal | C13: >300 MW | D13: 42 | E13: 7 | F13: 7 | G13: 20 | H13: 20 | I13: 8 | J13: 60 | K13: 14
B14: Supercritical Coal | C14: <500 MW | D14: 45 | E14: 6 | F14: 6 | G14: 25 | H14: 25 | I14: 6 | J14: 50 | K14: 12
... B16: Nuclear | C16: All | D16: 70 | E16: 24 | F16: 24 | G16: 5 | H16: 5 | I16: 48 | J16: 100 | K16: 50
B20: 🔖 Key References for Operational Parameters of Thermal Technologies
B22: Reference | C22: Description | D22: Parameters Covered
B23: IEA ETSAP Technology Briefs (e.g., E02, E03, E05, E07) | C23: Widely used briefs that summarize techno-economic characteristics of major generation technologies | D23: Startup time and cost, ramp rates, min stable load, etc.
B24: U.S. EIA Technical Reports (e.g., Assumptions to AEO, Form EIA-860/923) | C24: Contains data from U.S. fleet on heat rates, operational characteristics, startup times/costs, and outage rates | D24: Startup time/costs, min up/down times, ramp rates
B25: NREL ATB (Annual Technology Baseline) | C25: While primarily focused on cost and performance, some dispatch flexibility data is included | D25: Ramp rates, capacity factors
B26: NERA & NETL Reports (especially NETL reports on advanced coal/gas systems) | C26: NETL reports provide highly detailed operational and cost breakdowns of fossil fuel plants | D26: Startup costs, ramping behavior, part-load penalties
B27: ReEDS and PLEXOS modeling assumptions | C27: Often used in regulatory and utility planning models | D27: Min up/down time, ramping rates, min stable output
B28: OpenENTRANCE & ENTSO-E Data Sets | C28: Used in European modeling projects | D28: Plant dispatch constraints and operational flexibility
B29: Unit-specific data from GEM and NEEDS (U.S. EPA) | C29: Detailed asset-level characteristics | D29: Used for heat rates and sometimes ramp rates
B30: Academic Sources:
B32: P. Denholm et al. (NREL): Flexibility in 21st Century Power Systems
B34: W. Cole et al. (NREL): Operational Constraints in Electric Sector Capacity Expansion Models
B36: A. Sahoo et al. (Elsevier): Optimal scheduling of thermal units
B40: 📌 Notes on Estimation Approach:
B42: Where data was not available by size class, values were interpolated or inferred from fleet-wide averages or engineering rule-of-thumb ranges.
B44: Coal and gas plant behavior varies significantly by technology and age. For example, supercritical units often have tighter ramping constraints than newer combined cycle plants.
B46: Start-up cost/time estimates are especially variable depending on hot/warm/cold starts — values provided are typical warm start assumptions.

Sheet dcost_data
A1: technology | B1: Size Class | C1: decomissioning_cost
A2: OCGT (Peaker) | B2: <50 MW | C2: 50
A3: OCGT (Peaker) | B3: 50-200 MW | C3: 40
A4: OCGT (Peaker) | B4: >200 MW | C4: 30
A5: CCGT | B5: <300 MW | C5: 60
A6: CCGT | B6: >300 MW | C6: 50
A7: Gas/Oil Steam | B7: <200 MW | C7: 70
A8: Gas/Oil Steam | B8: >200 MW | C8: 60
A9: Diesel | B9: <20 MW | C9: 40
A10: Diesel | B10: >20 MW | C10: 30
A11: Subcritical Coal | B11: <300 MW | C11: 100
A12: Subcritical Coal | B12: >300 MW | C12: 90
A13: Supercritical Coal | B13: <500 MW | C13: 110
... A15: Nuclear | B15: All | C15: 500

Sheet readme_dcost
A1: Decommissioning Cost Estimates for Thermal Power Technologies (in 2023 USD)
A3: Technology | B3: Decommissioning Cost ($/kW) | C3: Variation by Plant Size | D3: Regional Differences | E3: Notes / Uncertainty (Regulatory Factors)
A4: ep_bioenergy (Biomass power plant) | B4: Limited data. Estimated on the order of ~$50–150/kW (small biomass plants) based on analogous thermal plant costs. | C4: Higher $/kW for small units (many biomass plants are 20–50 MW) due to fixed dismantling costs spread over fewer kW. Larger biomass facilities (if any) would see somewhat lower unit costs. | D4: Likely higher in regions with strict environmental remediation (e.g. North America, EU) and higher labor costs; potentially lower in regions with lower labor cost or less stringent site cleanup requirements (no specific quantified data found). | E4: No direct sources for biomass decommissioning cost; expected to be similar magnitude to retiring small coal-fired plants (tens of $/kW) in the absence of unique additional requirements. Environmental cleanup is generally simpler than coal (no coal ash), but biomass ash/soil remediation may still be needed if mandated.
A5: ep_coal_CFB (Coal – Circulating Fluidized Bed) | B5: Roughly $100/kW as a typical benchmark (within the general cost range for coal plants). Actual costs vary widely: U.S. data show ~$20–$466 per kW across different coal sites. CFB units, often mid-sized, likely fall in the mid-to-upper part of this range. | C5: Smaller CFB units (e.g. <300 MW) tend to have higher per-kW costs than large coal units, due to fewer MW to absorb fixed decommissioning expenses. (CFB plants are usually smaller than supercritical units.) Larger CFB installations would benefit from some economies of scale, lowering $/kW. | D5: Similar regional pattern as other coal: developed regions with stringent rules incur higher costs. For example, U.S. coal plant retirements average ~$117/kW, whereas an Indian coal plant of comparable size was estimated around $58/kW (roughly half the U.S. cost). EU costs appear intermediate (Germany’s phase-out auction yielded ~€66,000/MW or ~$66/kW on average). Lower labor costs and less extensive remediation in some developing countries can reduce overall costs. | E5: CFB decommissioning requirements are similar to other coal plants (demolition, ash and waste removal). CFB boilers have extensive refractory material to dispose of, but they lack the large “wet” ash ponds of older coal plants. Environmental regulations (air toxics, ash disposal) in U.S./EU require full site remediation (ash/FGD byproducts removal, soil cleanup), adding significant cost. Salvage of scrap metal (boilers, turbines) provides credit that can offset demolition costs. Overall uncertainty is high – site-specific factors (extent of contamination, legacy ash ponds) cause a wide cost range.
A6: ep_coal_IGCC (Coal – Integrated Gasification Combined Cycle) | B6: No specific case data available. Expected high end of coal cost range, potentially on the order of ~$150–200/kW (higher complexity). This would exceed typical pulverized coal plant costs. | C6: IGCC plants are relatively complex (gasifier, air separation, etc.) but often mid-sized (250–600 MW). The lack of large capacity units means limited economy of scale – $/kW likely higher than for a large conventional coal unit. | D6: Regional differences follow general coal trends: higher in OECD regions due to strict cleanup of any chemical process areas. Developing regions might see lower labor costs, but any savings could be offset if specialized handling of gasifier byproducts is needed. | E6: IGCC decommissioning involves removing not only the power island but also chemical process equipment (gasifiers, acid gas cleanup units) and managing any residual toxic materials (e.g. slag, sulfur byproducts). This adds scope and cost. With no real-world IGCC plant fully decommissioned yet, estimates are based on engineering judgment. Uncertainty is high. (Likely >10–20% cost premium over conventional coal of similar size is a reasonable assumption.)
A7: ep_coal_subcritical (Coal – Subcritical PC boiler) | B7: ~$100–120/kW as a typical value in advanced economies. Older subcritical plants often incur higher unit costs than modern plants. U.S. average was $117/kW (2016$). Range is very broad ($20 up to $466 per kW reported) depending on site conditions (salvage vs. remediation-heavy scenarios). | C7: Smaller/older subcritical units (e.g. 100–300 MW) have higher $/kW due to diseconomies of scale and often more extensive contamination (decades of coal ash handling). Larger subcritical plants approach costs of supercritical units on a per-kW basis. Economies of scale are evident – larger capacity means lower unit cost. | D7: North America: High end – U.S. plants ~$100–120/kW on average, due to strict environmental remediation (coal ash pond closures, etc.). Europe: Similar order of magnitude; e.g. German hard coal closures compensated at ~€66/kW on average. Asia: Lower – e.g. India ~$58/kW for a 1,000 MW plant (approximately half U.S. cost), reflecting cheaper labor and potentially less stringent cleanup standards. | E7: Subcritical coal plants often have extensive coal ash impoundments and legacy pollution, making remediation costly. New U.S. regulations for ash pond closure can double decommissioning costs (ash disposal can rival the rest of the project cost). Regulatory requirements to remove asbestos, remediate soil and groundwater, etc., are rigorous in NA/EU, driving up costs. Conversely, salvage of equipment and scrap steel can offset a portion of costs – in some cases well-run projects have net costs as low as ~$20/kW after salvage. Uncertainty: very high. In worst cases (extensive contamination), costs up to ~$450/kW were observed. In best cases (valuable scrap, minimal cleanup), net costs can be relatively low.
A8: ep_coal_subcritical_CCS (Coal – Subcritical with Carbon Capture) | B8: No decommissioning precedent. Expected to exceed subcritical costs by ~15–30%. If a subcritical w/o CCS is ~$100+ per kW, adding CCS equipment likely raises total to roughly $120–150+ per kW (estimated). | C8: A CCS retrofit or addition introduces large fixed assets (capture plant) that do not scale down well. For smaller subcritical units, the extra $/kW burden of dismantling CCS is high. Larger subcritical+CCS units would spread the CCS decommissioning cost over more capacity, somewhat reducing the per-kW impact. | D8: Developed regions will incur added cost to decommission CO₂ capture systems (and to handle amine solvents or other chemicals per environmental rules). Developing regions might have lower labor cost, but the technical complexity of CCS dismantling is similar globally. | E8: Decommissioning a CCS-equipped plant requires removing the CO₂ capture plant, compression units, and possibly CO₂ pipelines/injection wells. This adds significant scope. Industry assumptions for CO₂ storage sites use ~15% of CAPEX as decommissioning cost for that equipment, indicating a notable cost add-on. Regulatory: disposal of used solvent (amines), cleaning of capture equipment, and sealing any CO₂ injection wells must meet environmental standards. Uncertainty is very high, as no subcritical CCS plant has been fully retired yet.
A9: ep_coal_supercritical (Coal – Supercritical PC) | B9: ~$80–100/kW (estimated). In practice falls in the same wide cost range as other coal plants (~$50–150+/kW), but supercritical units tend to be larger/newer, often achieving lower $/kW than older subcritical plants. | C9: Supercritical units are typically large (500–800 MW), yielding better economies of scale – lower decommissioning cost per kW compared to smaller units. A large, modern plant might be closer to the lower end of coal $/kW costs. | D9: Regional differences mirror general coal trends. U.S./EU costs include full remediation; e.g. a 600 MW supercritical in the U.S. would likely be ~$100/kW. In lower-cost regions, perhaps 30–50% less in $/kW terms. (No tech-specific regional data, but the variation would be proportional to the base coal cost differences noted above.) | E9: Supercritical plants have similar decommissioning scope as subcritical (demolition, ash removal, site restore). Because many supercritical plants are newer, they may contain less asbestos and have better-designed ash handling, potentially easing remediation somewhat. Regulatory factors (ash disposal, emissions cleanup) still apply fully. Uncertainty comes from site specifics, but being newer/larger, supercritical unit decommissioning costs are expected to cluster in the mid-range for coal.
A10: ep_coal_supercritical_CCS (Coal – Supercritical with CCS) | B10: No direct data. Estimated ~15%+ above a comparable supercritical plant. For example, if ~$90/kW without CCS, then roughly $110–130/kW with CCS (order-of-magnitude). | C10: Large supercritical units (e.g. 500–800 MW) would dilute the added CCS removal cost somewhat, but CCS still adds a significant fixed decommissioning scope. The per-kW penalty might be slightly less (in percentage) than for smaller subcritical CCS, but still double-digit percent increase. | D10: Same pattern: high-regulation regions must safely dismantle and dispose of CCS infrastructure (and manage any CO₂ storage sites) – adding cost. Lower-cost regions benefit from cheaper labor but still face the technical tasks of CCS dismantling. | E10: Scope includes removal of extensive CCS hardware (large solvent contactors, compressors, etc.) and rehabilitation of any CO₂ sequestration facilities. Regulatory requirements (e.g. handling of amine solvent wastes, verification that no CO₂ leakage from storage) could impose additional steps. Since no supercritical+CCS plant has been retired yet, these figures are speculative. A ~15% of capital cost rule-of-thumb for CCS decommissioning has been used in absence of real data.
A11: ep_coal_ultra-supercritical (Coal – Ultra-supercritical PC) | B11: ~$60–90/kW (estimated). Ultra-supercritical units are very large and modern (often 800–1000+ MW), so they likely achieve the lowest $/kW among coal plants, barring site-specific complications. (No specific cases recorded yet; expectation is within the general coal range, but at the lower end). | C11: Excellent economies of scale – a 1000 MW ultra-supercritical plant spreads fixed decommissioning costs widely. If multiple units are on one site, costs per kW drop further. That said, the absolute cost is high (because these are huge plants). | D11: In North America/Europe, few ultra-supercritical plants exist; one example is Germany’s 800 MW Moorburg plant (commissioned 2015, retired 2021) which received ~€150k/MW in the closure auction (upper end bid) and contributed to an average ~€66k/MW payout – implying costs in that range. In Asia, ultra-supercritical units are being built but not yet decomissioned; future costs could be lower in $/kW due to cheaper labor, but stringent cleanup (if enforced) could raise them. | E11: Ultra-supercritical designs don’t fundamentally change decommissioning tasks versus other coal plants – still need to demolish boiler, turbine, clean up ash and wastewater, etc. However, being newer, they may have less environmental legacies (e.g. lined landfills for ash, modern wastewater treatment) which can simplify site restoration. Regulatory: Same framework (ash, emissions cleanup). Since none has a long operational legacy, there is uncertainty but likely fewer unknown liabilities.
A12: ep_coal_ultra-supercritical_CCS (Coal – Ultra-supercritical with CCS) | B12: No data (no such plant fully retired). Likely ~10–20% higher $/kW than ultra-supercritical without CCS, keeping it in roughly the ~$80–120/kW range (rough estimate). | C12: An ultra-supercritical + CCS unit would typically be very large, so while the absolute added cost of CCS removal is big, the per-kW impact is somewhat moderated by scale. Still, expect a notable increase in cost vs. non-CCS. | D12: Regional differences presumed similar: in high-regulation regions, careful decommissioning of advanced CCS systems (plus any CO₂ storage closure) will add significant cost; in lower-cost regions, labor is cheaper but the complexity remains. | E12: This scenario is hypothetical – no ultra-supercritical w/ CCS has been decommissioned. The additional CCS decommissioning requirements (as noted for other CCS cases: dismantling capture plant, handling chemicals, closing CO₂ injection wells) would apply. Using the ~15% of capex rule for CCS decommissioning, one can gauge the order of magnitude of added cost. Regulations would demand verification that the site (including CO₂ storage) is safely closed and remediated. Uncertainty is extremely high due to lack of precedent.
A13: ep_geothermal (Geothermal power plant) | B13: Sparse data. Likely on the order of tens of $/kW (lower than most fossil plants). One study notes that little data exists, but coal plant decom costs are ~$50–160k/MW for comparison – geothermal is expected to be in a similar or lower range per MW. | C13: Decommissioning cost varies with the number and depth of wells: a field with many deep wells will incur more cost to plug them. Small geothermal plants (e.g. 20–50 MW) have fewer kW to spread fixed costs, so $/kW can be moderate. Larger geothermal facilities (few exist) would improve $/kW somewhat. | D13: No known regional cost studies. Generally, labor rates influence cost – e.g. plugging geothermal wells in North America/EU is more expensive than in developing countries. However, overall costs are lower than coal, so differences may be less dramatic in absolute $/kW. | E13: Geothermal decommissioning involves removing the power station (turbine, cooling towers, etc.) and plugging geothermal wells to prevent leaks. Well plugging costs about $20k per well plus $76k for proper abandonment cementing. For a 50 MW geothermal field (say 10–20 wells), well closure might cost <$1 million total ($20/kW). Environmental remediation is relatively straightforward (no fuel or ash contamination, though geothermal fluids can contain some minerals that require proper disposal). Regulatory: wells must be sealed to prevent contamination of aquifers, and surface equipment removed. The overall uncertainty is moderate – while site specifics vary, the absence of large contamination liabilities keeps costs in a tighter band.
A14: ep_nuclear (Nuclear power plant – large PWR/BWR) | B14: $750–1,250/kW for full radiological decommissioning of a large reactor (range from “optimistic” to “conservative” scenarios). This equates to on the order of $1–1.5 billion for a 1,000 MW reactor. Actual project data often fall in this range or higher – e.g. decommissioning two 1,100 MW reactors was estimated at $4.4 billion (~$2,000/kW). | C14: Some economies of scale exist: multi-unit sites or very large reactors achieve slightly lower $/kW than small reactors. (Early small reactors had much higher per-kW costs – e.g. UK Magnox units cost 5× more per kW than typical light-water reactors). Nonetheless, even the largest units incur hundreds of $/kW. The bulk of cost is fixed (reactor vessel removal, site cleanup) and does not scale down linearly. | D14: North America: typical reactor decom ~$300–500+ million per unit (roughly $300–600/kW). However, many recent U.S. estimates are higher (near $1,000/kW) due to stringent cleanup and waste disposal costs. Europe: similar or higher – EU reports often budget ~€1–1.5 billion per 1 GW (≈$1,100–1,600/kW). Some countries under-provisioned funds, showing how high costs can run. Asia: varies – Japan’s Fukushima-related decom will be enormous; other countries (e.g. India, China) historically assumed lower costs (~10% of capital cost, which was ~$100–200/kW in older estimates), but actual required funds may be higher with today’s safety standards. | E14: Nuclear decommissioning is complex and highly regulated. It involves removing and disposing of activated reactor components, decontaminating the site to release it for other use, and managing radioactive waste (spent fuel remains in storage). Regulations often allow up to 60 years for decommissioning (SAFSTOR vs immediate dismantling strategies) to reduce radiation levels, but ultimately the site must be cleaned to regulatory thresholds. Waste handling and long-term radiological monitoring/storage dominate costs. Funds are typically accumulated over the plant’s life, but many jurisdictions have shortfalls. Uncertainty is significant – unforeseen contamination (e.g. in soil or groundwater) can drive costs up. However, unlike fossil plants, cost ranges are somewhat bounded by detailed decommissioning plans: for large PWR/BWR reactors, $750–1250/kW is a commonly cited planning range.
... A23: ep_oil_steam_turbine (Oil-fired boiler + steam turbine) | B23: ~$30–100/kW (widely variable). These plants can approach coal-plant decommissioning costs if large fuel oil contamination issues exist. Typical cases might be in the $50–70/kW range. U.S. data for “petroleum” plants (some of which are oil steam units) show up to ~$100+kW in the high end. | C23: Oil-fired steam stations were often built mid-20th century (100–400 MW). Smaller ones have higher unit costs (and many were small peaking steam units). Larger oil-fired power stations (e.g. some 600 MW units in the past) benefit from scale but still carry significant fixed costs for tank removals, etc. If multiple units share a tank farm, that helps spread the remediation cost. | D23: In strict regions (North America, Europe), environmental remediation is the big driver – removal of massive fuel oil tanks, cleanup of oil leaks (which were not uncommon at old facilities), and asbestos removal all must be done. This can make costs substantial, sometimes comparable to a coal plant’s. In regions with fewer environmental requirements, an owner might simply demolish the structures and leave site soil as-is, significantly cutting cost (though leaving liabilities). Labor cost differences also apply, but the major expense is in remediation efforts which use substantial materials and heavy equipment. | E23: Decommissioning an oil-fired steam plant entails demolishing the boiler, turbine, and ancillary structures similar to any steam plant. Additionally, fuel storage infrastructure (which can be extensive – large oil tanks, pumping systems, pipelines) must be dismantled. Soil and groundwater remediation can be challenging if oil seeped into ground over years. Oil can create a long-term pollution plume, so regulations require thorough cleanup (soil excavation or in-situ treatment) in many jurisdictions. This is labor- and cost-intensive and is often the largest single cost item, much like coal ash is for coal plants. Salvage helps (old oil tanks can be scrapped, equipment sold), but it may not offset the high cleanup costs. Uncertainty is high, hinging on how contaminated the site is. Some old oil plants that operated only sparingly may have minimal contamination and thus be relatively cheap to retire (~$30–40/kW), whereas others that ran for decades and leaked oil could be at the upper end or beyond.

Sheet uc_tech_map
A1: technology | B1: model_name
A2: CCGT | B2: ep_gas_combined_cycle,ep_oil_combined_cycle
A3: Diesel | B3: ep_gas_internal_combustion,ep_oil_internal_combustion
A4: Gas/Oil Steam | B4: ep_gas_steam_turbine,ep_oil_steam_turbine
A5: Nuclear | B5: ep_nuclear,ep_nuclear_smr
A6: OCGT (Peaker) | B6: ep_gas_gas_turbine,ep_oil_gas_turbine
A7: Subcritical Coal | B7: ep_bioenergy,ep_coal_CFB,ep_coal_IGCC,ep_coal_subcritical,ep_coal_subcritical_CCS
A8: Supercritical Coal | B8: ep_coal_supercritical,ep_coal_supercritical_CCS,ep_coal_ultra-supercritical,ep_coal_ultra-supercritical_CCS

Sheet DEF topology
B3: ~TFM_TOPINS
B4: process | C4: commodity | D4: io
B5: *stg8hb* | C5: ELC4H,ELC8H,ELC | D5: IN
B6: *stg4hb* | C6: ELC4H,ELC | D6: IN
B7: distr* | C7: ELC4H,ELC8H | D7: OUT
B17: ~UC_Sets: R_E: AllRegions
H20: ~UC_T: LO
B21: UC_N | C21: PSET_SET | D21: PSET_PN | E21: Pset_CI | F21: PSET_CO | G21: Cset_CN | H21: TimeSlice | I21: UC_CAP | J21: UC_COMPRD | K21: UC_RHSRT | L21: UC_RHSRT~0 | M21: UC_Desc
B22: UCE_Min-DispatchableCAP | C22: ELE,CHP | E22: *,-solar,-wind*,-ELC,-ELCSPV,-elc[_]???[_]*,-e[_]* | I22: 1 | K22: 0 | L22: 5 | M22: Min dispatchable capacity for VRE portfolio
G23: DEF_C | J23: -1
